Workbook

Sheet Gastos e Ingresos
A1: Canavida Villas & Resort – Gastos e Ingresos
A2: Periodo: 5 de octubre al 31 de diciembre de 2026 · Moneda: USD · Todo se calcula desde las hojas de registro diario. · Control de efectivo en las hojas Caja Efectivo y Arqueo y Resumen Caja.
A4: INGRESOS | B4: =Listas!$K$5 -> Octubre 2026 | C4: =Listas!$K$6 -> Noviembre 2026 | D4: =Listas!$K$7 -> Diciembre 2026 | E4: Total | F4: % del total
A5: Cleaning Fee | B5: 70 | C5: =SUMIFS('Ingresos Diarios'!$H$27:$H$1026,'Ingresos Diarios'!$C$27:$C$1026,$A5,'Ingresos Diarios'!$A$27:$A$1026,">="&Listas!$L$6,'Ingresos Diarios'!$A$27:$A$1026,"<="&Listas!$M$6) -> 0 | D5: =SUMIFS('Ingresos Diarios'!$H$27:$H$1026,'Ingresos Diarios'!$C$27:$C$1026,$A5,'Ingresos Diarios'!$A$27:$A$1026,">="&Listas!$L$7,'Ingresos Diarios'!$A$27:$A$1026,"<="&Listas!$M$7) -> 0 | E5: =SUM(B5:D5) -> 70 | F5: =IF($E$10=0,0,E5/$E$10) -> 0.0025425453
A6: Early/Late Check Out | B6: =SUMIFS('Ingresos Diarios'!$H$27:$H$1026,'Ingresos Diarios'!$C$27:$C$1026,$A6,'Ingresos Diarios'!$A$27:$A$1026,">="&Listas!$L$5,'Ingresos Diarios'!$A$27:$A$1026,"<="&Listas!$M$5) -> 150.46623 | C6: =SUMIFS('Ingresos Diarios'!$H$27:$H$1026,'Ingresos Diarios'!$C$27:$C$1026,$A6,'Ingresos Diarios'!$A$27:$A$1026,">="&Listas!$L$6,'Ingresos Diarios'!$A$27:$A$1026,"<="&Listas!$M$6) -> 0 | D6: =SUMIFS('Ingresos Diarios'!$H$27:$H$1026,'Ingresos Diarios'!$C$27:$C$1026,$A6,'Ingresos Diarios'!$A$27:$A$1026,">="&Listas!$L$7,'Ingresos Diarios'!$A$27:$A$1026,"<="&Listas!$M$7) -> 0 | E6: =SUM(B6:D6) -> 150.46623 | F6: =IF($E$10=0,0,E6/$E$10) -> 0.0054652458
A7: Hospedaje | B7: 27227 | C7: =SUMIFS('Ingresos Diarios'!$H$27:$H$1026,'Ingresos Diarios'!$C$27:$C$1026,$A7,'Ingresos Diarios'!$A$27:$A$1026,">="&Listas!$L$6,'Ingresos Diarios'!$A$27:$A$1026,"<="&Listas!$M$6) -> 0 | D7: =SUMIFS('Ingresos Diarios'!$H$27:$H$1026,'Ingresos Diarios'!$C$27:$C$1026,$A7,'Ingresos Diarios'!$A$27:$A$1026,">="&Listas!$L$7,'Ingresos Diarios'!$A$27:$A$1026,"<="&Listas!$M$7) -> 0 | E7: =SUM(B7:D7) -> 27227 | F7: =IF($E$10=0,0,E7/$E$10) -> 0.98894115
A8: Mascota | B8: 64 | C8: =SUMIFS('Ingresos Diarios'!$H$27:$H$1026,'Ingresos Diarios'!$C$27:$C$1026,$A8,'Ingresos Diarios'!$A$27:$A$1026,">="&Listas!$L$6,'Ingresos Diarios'!$A$27:$A$1026,"<="&Listas!$M$6) -> 0 | D8: =SUMIFS('Ingresos Diarios'!$H$27:$H$1026,'Ingresos Diarios'!$C$27:$C$1026,$A8,'Ingresos Diarios'!$A$27:$A$1026,">="&Listas!$L$7,'Ingresos Diarios'!$A$27:$A$1026,"<="&Listas!$M$7) -> 0 | E8: =SUM(B8:D8) -> 64 | F8: =IF($E$10=0,0,E8/$E$10) -> 0.0023246128
A9: Tours y actividades | B9: =SUMIFS('Ingresos Diarios'!$H$27:$H$1026,'Ingresos Diarios'!$C$27:$C$1026,$A9,'Ingresos Diarios'!$A$27:$A$1026,">="&Listas!$L$5,'Ingresos Diarios'!$A$27:$A$1026,"<="&Listas!$M$5) -> 20 | C9: =SUMIFS('Ingresos Diarios'!$H$27:$H$1026,'Ingresos Diarios'!$C$27:$C$1026,$A9,'Ingresos Diarios'!$A$27:$A$1026,">="&Listas!$L$6,'Ingresos Diarios'!$A$27:$A$1026,"<="&Listas!$M$6) -> 0 | D9: =SUMIFS('Ingresos Diarios'!$H$27:$H$1026,'Ingresos Diarios'!$C$27:$C$1026,$A9,'Ingresos Diarios'!$A$27:$A$1026,">="&Listas!$L$7,'Ingresos Diarios'!$A$27:$A$1026,"<="&Listas!$M$7) -> 0 | E9: =SUM(B9:D9) -> 20 | F9: =IF($E$10=0,0,E9/$E$10) -> 0.00072644151
A10: TOTAL INGRESOS | B10: =SUM(B5:B9) -> 27531.466 | C10: =SUM(C5:C9) -> 0 | D10: =SUM(D5:D9) -> 0 | E10: =SUM(E5:E9) -> 27531.466 | F10: =IF($E$10=0,0,E10/$E$10) -> 1
A12: GASTOS | B12: =Listas!$K$5 -> Octubre 2026 | C12: =Listas!$K$6 -> Noviembre 2026 | D12: =Listas!$K$7 -> Diciembre 2026 | E12: Total | F12: % del total
A13: Alimentos y bebidas | B13: 2167 | C13: =SUMIFS('Gastos Diarios'!$F$35:$F$1049,'Gastos Diarios'!$B$35:$B$1049,$A13,'Gastos Diarios'!$A$35:$A$1049,">="&Listas!$L$6,'Gastos Diarios'!$A$35:$A$1049,"<="&Listas!$M$6) -> 0 | D13: =SUMIFS('Gastos Diarios'!$F$35:$F$1049,'Gastos Diarios'!$B$35:$B$1049,$A13,'Gastos Diarios'!$A$35:$A$1049,">="&Listas!$L$7,'Gastos Diarios'!$A$35:$A$1049,"<="&Listas!$M$7) -> 0 | E13: =SUM(B13:D13) -> 2167 | F13: =IF($E$25=0,0,E13/$E$25) -> 0.056772334
A14: Combustible y transporte | B14: 564 | C14: =SUMIFS('Gastos Diarios'!$F$35:$F$1049,'Gastos Diarios'!$B$35:$B$1049,$A14,'Gastos Diarios'!$A$35:$A$1049,">="&Listas!$L$6,'Gastos Diarios'!$A$35:$A$1049,"<="&Listas!$M$6) -> 0 | D14: =SUMIFS('Gastos Diarios'!$F$35:$F$1049,'Gastos Diarios'!$B$35:$B$1049,$A14,'Gastos Diarios'!$A$35:$A$1049,">="&Listas!$L$7,'Gastos Diarios'!$A$35:$A$1049,"<="&Listas!$M$7) -> 0 | E14: =SUM(B14:D14) -> 564 | F14: =IF($E$25=0,0,E14/$E$25) -> 0.014776002
A15: Comisiones de plataformas | B15: 2825 | C15: =SUMIFS('Gastos Diarios'!$F$35:$F$1049,'Gastos Diarios'!$B$35:$B$1049,$A15,'Gastos Diarios'!$A$35:$A$1049,">="&Listas!$L$6,'Gastos Diarios'!$A$35:$A$1049,"<="&Listas!$M$6) -> 0 | D15: =SUMIFS('Gastos Diarios'!$F$35:$F$1049,'Gastos Diarios'!$B$35:$B$1049,$A15,'Gastos Diarios'!$A$35:$A$1049,">="&Listas!$L$7,'Gastos Diarios'!$A$35:$A$1049,"<="&Listas!$M$7) -> 0 | E15: =SUM(B15:D15) -> 2825 | F15: =IF($E$25=0,0,E15/$E$25) -> 0.074011003
A16: Imprevistos y otros | B16: 3548 | C16: =SUMIFS('Gastos Diarios'!$F$35:$F$1049,'Gastos Diarios'!$B$35:$B$1049,$A16,'Gastos Diarios'!$A$35:$A$1049,">="&Listas!$L$6,'Gastos Diarios'!$A$35:$A$1049,"<="&Listas!$M$6) -> 0 | D16: =SUMIFS('Gastos Diarios'!$F$35:$F$1049,'Gastos Diarios'!$B$35:$B$1049,$A16,'Gastos Diarios'!$A$35:$A$1049,">="&Listas!$L$7,'Gastos Diarios'!$A$35:$A$1049,"<="&Listas!$M$7) -> 0 | E16: =SUM(B16:D16) -> 3548 | F16: =IF($E$25=0,0,E16/$E$25) -> 0.092952581
A17: Jardinería y piscinas | B17: 469 | C17: =SUMIFS('Gastos Diarios'!$F$35:$F$1049,'Gastos Diarios'!$B$35:$B$1049,$A17,'Gastos Diarios'!$A$35:$A$1049,">="&Listas!$L$6,'Gastos Diarios'!$A$35:$A$1049,"<="&Listas!$M$6) -> 0 | D17: =SUMIFS('Gastos Diarios'!$F$35:$F$1049,'Gastos Diarios'!$B$35:$B$1049,$A17,'Gastos Diarios'!$A$35:$A$1049,">="&Listas!$L$7,'Gastos Diarios'!$A$35:$A$1049,"<="&Listas!$M$7) -> 0 | E17: =SUM(B17:D17) -> 469 | F17: =IF($E$25=0,0,E17/$E$25) -> 0.012287136
A18: Limpieza y lavandería | B18: 542 | C18: =SUMIFS('Gastos Diarios'!$F$35:$F$1049,'Gastos Diarios'!$B$35:$B$1049,$A18,'Gastos Diarios'!$A$35:$A$1049,">="&Listas!$L$6,'Gastos Diarios'!$A$35:$A$1049,"<="&Listas!$M$6) -> 0 | D18: =SUMIFS('Gastos Diarios'!$F$35:$F$1049,'Gastos Diarios'!$B$35:$B$1049,$A18,'Gastos Diarios'!$A$35:$A$1049,">="&Listas!$L$7,'Gastos Diarios'!$A$35:$A$1049,"<="&Listas!$M$7) -> 0 | E18: =SUM(B18:D18) -> 542 | F18: =IF($E$25=0,0,E18/$E$25) -> 0.014199633
A19: Mantenimiento y reparaciones | B19: 8662 | C19: =SUMIFS('Gastos Diarios'!$F$35:$F$1049,'Gastos Diarios'!$B$35:$B$1049,$A19,'Gastos Diarios'!$A$35:$A$1049,">="&Listas!$L$6,'Gastos Diarios'!$A$35:$A$1049,"<="&Listas!$M$6) -> 0 | D19: =SUMIFS('Gastos Diarios'!$F$35:$F$1049,'Gastos Diarios'!$B$35:$B$1049,$A19,'Gastos Diarios'!$A$35:$A$1049,">="&Listas!$L$7,'Gastos Diarios'!$A$35:$A$1049,"<="&Listas!$M$7) -> 0 | E19: =SUM(B19:D19) -> 8662 | F19: =IF($E$25=0,0,E19/$E$25) -> 0.22693215
A20: Muebleria | B20: 321 | C20: =SUMIFS('Gastos Diarios'!$F$35:$F$1049,'Gastos Diarios'!$B$35:$B$1049,$A20,'Gastos Diarios'!$A$35:$A$1049,">="&Listas!$L$6,'Gastos Diarios'!$A$35:$A$1049,"<="&Listas!$M$6) -> 0 | D20: =SUMIFS('Gastos Diarios'!$F$35:$F$1049,'Gastos Diarios'!$B$35:$B$1049,$A20,'Gastos Diarios'!$A$35:$A$1049,">="&Listas!$L$7,'Gastos Diarios'!$A$35:$A$1049,"<="&Listas!$M$7) -> 0 | E20: =SUM(B20:D20) -> 321 | F20: =IF($E$25=0,0,E20/$E$25) -> 0.0084097459
A21: Nómina y salarios | B21: 8000 | C21: =SUMIFS('Gastos Diarios'!$F$35:$F$1049,'Gastos Diarios'!$B$35:$B$1049,$A21,'Gastos Diarios'!$A$35:$A$1049,">="&Listas!$L$6,'Gastos Diarios'!$A$35:$A$1049,"<="&Listas!$M$6) -> 0 | D21: =SUMIFS('Gastos Diarios'!$F$35:$F$1049,'Gastos Diarios'!$B$35:$B$1049,$A21,'Gastos Diarios'!$A$35:$A$1049,">="&Listas!$L$7,'Gastos Diarios'!$A$35:$A$1049,"<="&Listas!$M$7) -> 0 | E21: =SUM(B21:D21) -> 8000 | F21: =IF($E$25=0,0,E21/$E$25) -> 0.20958868
A22: Servicios públicos e internet | B22: 2588 | C22: =SUMIFS('Gastos Diarios'!$F$35:$F$1049,'Gastos Diarios'!$B$35:$B$1049,$A22,'Gastos Diarios'!$A$35:$A$1049,">="&Listas!$L$6,'Gastos Diarios'!$A$35:$A$1049,"<="&Listas!$M$6) -> 0 | D22: =SUMIFS('Gastos Diarios'!$F$35:$F$1049,'Gastos Diarios'!$B$35:$B$1049,$A22,'Gastos Diarios'!$A$35:$A$1049,">="&Listas!$L$7,'Gastos Diarios'!$A$35:$A$1049,"<="&Listas!$M$7) -> 0 | E22: =SUM(B22:D22) -> 2588 | F22: =IF($E$25=0,0,E22/$E$25) -> 0.067801939
A23: Software y tecnología | B23: 2194 | C23: =SUMIFS('Gastos Diarios'!$F$35:$F$1049,'Gastos Diarios'!$B$35:$B$1049,$A23,'Gastos Diarios'!$A$35:$A$1049,">="&Listas!$L$6,'Gastos Diarios'!$A$35:$A$1049,"<="&Listas!$M$6) -> 0 | D23: =SUMIFS('Gastos Diarios'!$F$35:$F$1049,'Gastos Diarios'!$B$35:$B$1049,$A23,'Gastos Diarios'!$A$35:$A$1049,">="&Listas!$L$7,'Gastos Diarios'!$A$35:$A$1049,"<="&Listas!$M$7) -> 0 | E23: =SUM(B23:D23) -> 2194 | F23: =IF($E$25=0,0,E23/$E$25) -> 0.057479696
A24: Suministros y amenities | B24: 6290 | C24: =SUMIFS('Gastos Diarios'!$F$35:$F$1049,'Gastos Diarios'!$B$35:$B$1049,$A24,'Gastos Diarios'!$A$35:$A$1049,">="&Listas!$L$6,'Gastos Diarios'!$A$35:$A$1049,"<="&Listas!$M$6) -> 0 | D24: =SUMIFS('Gastos Diarios'!$F$35:$F$1049,'Gastos Diarios'!$B$35:$B$1049,$A24,'Gastos Diarios'!$A$35:$A$1049,">="&Listas!$L$7,'Gastos Diarios'!$A$35:$A$1049,"<="&Listas!$M$7) -> 0 | E24: =SUM(B24:D24) -> 6290 | F24: =IF($E$25=0,0,E24/$E$25) -> 0.1647891
A25: TOTAL GASTOS | B25: =SUM(B13:B24) -> 38170 | C25: =SUM(C13:C24) -> 0 | D25: =SUM(D13:D24) -> 0 | E25: =SUM(E13:E24) -> 38170 | F25: =IF($E$25=0,0,E25/$E$25) -> 1
A27: RESULTADO | B27: =Listas!$K$5 -> Octubre 2026 | C27: =Listas!$K$6 -> Noviembre 2026 | D27: =Listas!$K$7 -> Diciembre 2026 | E27: Total
A28: UTILIDAD NETA (Ingresos − Gastos) | B28: =B10-B25 -> -10638.534 | C28: =C10-C25 -> 0 | D28: =D10-D25 -> 0 | E28: =E10-E25 -> -10638.534
A29: Margen de utilidad (%) | B29: =IF(B10=0,0,B28/B10) -> -0.38641363 | C29: =IF(C10=0,0,C28/C10) -> 0 | D29: =IF(D10=0,0,D28/D10) -> 0 | E29: =IF(E10=0,0,E28/E10) -> -0.38641363

Sheet Gastos Diarios
A1: Registro de Gastos Diarios
A2: Una fila por gasto desde la fila 6 (celdas en azul). Fecha entre 05/10/2026 y 31/12/2026; categoría y método se eligen de la lista.
A3: 46300 | B3: Mantenimiento y reparaciones | C3: Reparación bomba de piscina Villa Toucan | D3: Ferretería Uvita | E3: Transferencia / SINPE | F3: 185.5 | G3: Fact. 0012345 | H3: ← Ejemplo (no se suma; puede borrarlo)
A4: Registros: | B4: =COUNT(A35:A1049) -> 100 | E4: TOTAL REGISTRADO | F4: =SUM(F35:F1049) -> 29452.747
A5: Fecha | B5: Categoría | C5: Descripción | D5: Proveedor | E5: Método de pago | F5: Monto (USD) | G5: Nº factura / Notas
A6: 46296 | B6: Mantenimiento y reparaciones | C6: Luces de Piscina | D6: Zebol | E6: Tarjeta | F6: 246 | G6: 7392 | H6: ?
A7: 46296 | B7: Suministros y amenities | C7: Articulos para habitaciones | D7: Ekono | E7: Tarjeta | F7: =66120/430 -> 153.76744 | G7: 64
A8: 46296 | B8: Software y tecnología | C8: Internet | D8: Wireless Comunications KVF | E8: Transferencia / SINPE | F8: 650 | G8: 15146
A9: 46296 | B9: Software y tecnología | C9: Camaras Seguridad | D9: Wireless Comunications KVF | E9: Transferencia / SINPE | F9: 289.68 | G9: 4799
A10: 46296 | B10: Software y tecnología | C10: Equipo de IT | D10: Wireless Comunications KVF | E10: Transferencia / SINPE | F10: 720.64 | G10: 4800
A11: 46297 | B11: Muebleria | C11: Thinner Corriente | D11: Sur Quimica | E11: Tarjeta | F11: 82.9 | G11: 2243
A12: 46297 | B12: Suministros y amenities | C12: Articulos para habitaciones | D12: Ekono | E12: Tarjeta | F12: =217835/430 -> 506.59302 | G12: 3268
A13: 46297 | B13: Suministros y amenities | C13: Articulos para habitaciones | D13: Ekono | E13: Tarjeta | F13: =217835/430 -> 506.59302 | G13: 2692
A14: 46297 | B14: Combustible y transporte | C14: Gasolina | D14: Coopeagri | E14: Tarjeta | F14: =10712/430 -> 24.911628 | G14: 3549
A15: 46298 | B15: Imprevistos y otros | C15: Reparacion de Llanta | D15: GS La Colonia | E15: Tarjeta | F15: =4000/430 -> 9.3023256 | G15: 29847
A16: 46299 | B16: Limpieza y lavandería | C16: Suministros | D16: Corporacion Supermercados Unidos | E16: Tarjeta | F16: =33930/430 -> 78.906977 | G16: 2855
A17: 46300 | B17: Alimentos y bebidas | C17: Pedido para alimentacion empleados | D17: Frutas y Verduras Generaleñas | E17: Tarjeta | F17: =52850/430 -> 122.90698 | G17: 36124
A18: 46300 | B18: Suministros y amenities | C18: Suministros Lavanderia | D18: Natural Center | E18: Tarjeta | F18: =212440/430 -> 494.04651 | G18: 292
A19: 46300 | B19: Suministros y amenities | C19: Articulos para habitaciones | D19: Ekono | E19: Tarjeta | F19: =217835/430 -> 506.59302 | G19: 102751
A20: 46300 | B20: Mantenimiento y reparaciones | C20: Materiales de Construccion | D20: Sur Quimica | E20: Tarjeta | F20: =122514/430 -> 284.91628 | G20: 2243
A21: 46300 | B21: Suministros y amenities | C21: Articulos para habitaciones | D21: Ekono | E21: Tarjeta | F21: =217835/430 -> 506.59302 | G21: 3270
A22: 46300 | B22: Suministros y amenities | C22: Materiales de Construccion | D22: Ferreteria Palmares | E22: Tarjeta | F22: =223608.27/430 -> 520.01923 | G22: 5905
A23: 46300 | B23: Suministros y amenities | C23: Materiales de Construccion | D23: Ferreteria Palmares | E23: Tarjeta | F23: =889202.16/430 -> 2067.912 | G23: 701
A24: 46301 | B24: Mantenimiento y reparaciones | C24: Materiales de Construccion | D24: Moncavel | E24: Efectivo | F24: =474600/430 -> 1103.7209 | G24: 3215
A25: 46301 | B25: Suministros y amenities | C25: Suministros Lavanderia | D25: Natural Center | E25: Tarjeta | F25: =85831/430 -> 199.60698 | G25: 40294
A26: 46302 | B26: Alimentos y bebidas | C26: Alimento Animales | D26: Michael Alberto Rodriguez | E26: Transferencia / SINPE | F26: =40680/430 -> 94.604651 | G26: 7932
A27: 46302 | B27: Alimentos y bebidas | C27: Pedido para alimentacion empleados | D27: BM Supermercado | E27: Tarjeta | F27: =76543/430 -> 178.00698 | G27: 4567
A28: 46302 | B28: Alimentos y bebidas | C28: Pedido para alimentacion empleados | D28: BM Supermercado | E28: Tarjeta | F28: =56242.13/430 -> 130.79565 | G28: 4567
A29: 46302 | B29: Alimentos y bebidas | C29: Pedido para alimentacion empleados | D29: BM Supermercado | E29: Tarjeta | F29: =88163.05/430 -> 205.03035 | G29: 4567
A30: 46302 | B30: Mantenimiento y reparaciones | C30: Faja Industrial | D30: RM Industrial Solin | E30: Tarjeta | F30: =12999/430 -> 30.230233 | G30: 4980
A31: 46302 | B31: Suministros y amenities | C31: Suministros Lavanderia | D31: Corporacion Supermercados Unidos | E31: Tarjeta | F31: =50670/430 -> 117.83721 | G31: 1307
A32: 46302 | B32: Suministros y amenities | C32: Suministros Lavanderia | D32: Pequeño Mundo | E32: Tarjeta | F32: =85900/430 -> 199.76744 | G32: 20597
A33: 46305 | B33: Alimentos y bebidas | C33: Gastos de representacion | D33: Supermercado Uvita | E33: Efectivo | F33: =7000/459 -> 15.250545 | G33: 44560
A34: 46305 | B34: Alimentos y bebidas | C34: Gastos de representacion | D34: Supermercado Uvita | E34: Efectivo | F34: =9300/459 -> 20.261438 | G34: 61880
A35: 46307 | B35: Alimentos y bebidas | C35: Pedido para alimentacion empleados | D35: Frutas y Verduras Generaleñas | E35: Transferencia / SINPE | F35: =64435/430 -> 149.84884 | G35: 1167
A36: 46307 | B36: Imprevistos y otros | C36: Servicio Profesionales Andres | D36: Canavida | E36: Efectivo | F36: =200000/430 -> 465.11628 | G36: 162721
A37: 46307 | B37: Alimentos y bebidas | C37: Gastos de representacion | D37: La Lico Happy Point | E37: Tarjeta | F37: =1900/459 -> 4.1394336 | G37: 624971
A38: 46307 | B38: Alimentos y bebidas | C38: Pedido para alimentacion empleados | D38: BM Supermercado | E38: Transferencia / SINPE | F38: =101799.78/430 -> 236.74367 | G38: 259324
A39: 46307 | B39: Muebleria | C39: Materiales de Construccion | D39: Sur Quimica | E39: Tarjeta | F39: =102452.96/430 -> 238.2627 | G39: 9999
A40: 46307 | B40: Software y tecnología | C40: Cargador de Laptop | D40: Repuestos Uvita | E40: Efectivo | F40: =18650/459 -> 40.631808 | G40: 70375
A41: 46308 | B41: Suministros y amenities | C41: Suministros Oficina | D41: Corporacion Supermercados Unidos | E41: Tarjeta | F41: =17650/430 -> 41.046512 | G41: 4665
A42: 46308 | B42: Imprevistos y otros | C42: Repuestos Maquina de presion de agua | D42: Sin Factura | E42: Efectivo | F42: =62100/430 -> 144.4186 | G42: 1307
A43: 46308 | B43: Alimentos y bebidas | C43: Gastos de representacion | D43: Repuestos Uvita | E43: Tarjeta | F43: =17000/459 -> 37.037037 | G43: 70399
A44: 46308 | B44: Alimentos y bebidas | C44: Gastos de representacion | D44: Maxi PAli | E44: Tarjeta | F44: =17650/459 -> 38.453159 | G44: 5274
A45: 46309 | B45: Combustible y transporte | C45: Gasolina | D45: GS La Colonia | E45: Efectivo | F45: =10527/459 -> 22.934641 | G45: 52754
A46: 46309 | B46: Suministros y amenities | C46: Articulos para habitaciones | D46: Mariana Lopez | E46: Tarjeta | F46: 7.17 | G46: 536
A47: 46309 | B47: Jardinería y piscinas | C47: Clarificador | D47: Felipe Abarca | E47: Tarjeta | F47: =203224/459 -> 442.75381 | G47: 11724
A48: 46309 | B48: Servicios públicos e internet | C48: Energia y alumbrado publico | D48: ICE | E48: Tarjeta | F48: =152470/459 -> 332.17865 | G48: 75655
A49: 46309 | B49: Servicios públicos e internet | C49: Energia y alumbrado publico | D49: ICE | E49: Tarjeta | F49: =78580/459 -> 171.19826 | G49: 75671
A50: 46309 | B50: Servicios públicos e internet | C50: Energia y alumbrado publico | D50: ICE | E50: Tarjeta | F50: =159500/459 -> 347.49455 | G50: 75704
A51: 46309 | B51: Servicios públicos e internet | C51: Energia y alumbrado publico | D51: ICE | E51: Tarjeta | F51: =50940/459 -> 110.98039 | G51: 75672
A52: 46309 | B52: Servicios públicos e internet | C52: Energia y alumbrado publico | D52: ICE | E52: Tarjeta | F52: =54335/459 -> 118.37691 | G52: 75679
A53: 46309 | B53: Servicios públicos e internet | C53: Energia y alumbrado publico | D53: ICE | E53: Tarjeta | F53: =4615/459 -> 10.054466 | G53: 75654
A54: 46309 | B54: Servicios públicos e internet | C54: Energia y alumbrado publico | D54: ICE | E54: Tarjeta | F54: =4615/459 -> 10.054466 | G54: 75657
A55: 46309 | B55: Servicios públicos e internet | C55: Energia y alumbrado publico | D55: ICE | E55: Tarjeta | F55: =4615/459 -> 10.054466 | G55: 75658
A56: 46309 | B56: Servicios públicos e internet | C56: Energia y alumbrado publico | D56: ICE | E56: Tarjeta | F56: =4615/459 -> 10.054466 | G56: 75667
A57: 46309 | B57: Servicios públicos e internet | C57: Energia y alumbrado publico | D57: ICE | E57: Tarjeta | F57: =91460/459 -> 199.25926 | G57: 75700
A58: 46309 | B58: Servicios públicos e internet | C58: Energia y alumbrado publico | D58: ICE | E58: Tarjeta | F58: =70850/459 -> 154.3573 | G58: 75709
A59: 46309 | B59: Servicios públicos e internet | C59: Energia y alumbrado publico | D59: ICE | E59: Tarjeta | F59: =4615/459 -> 10.054466 | G59: 75717
A60: 46309 | B60: Servicios públicos e internet | C60: Energia y alumbrado publico | D60: ICE | E60: Tarjeta | F60: =101880/459 -> 221.96078 | G60: 75724
A61: 46309 | B61: Servicios públicos e internet | C61: Energia y alumbrado publico | D61: ICE | E61: Tarjeta | F61: =14520/459 -> 31.633987 | G61: 75691
A62: 46309 | B62: Servicios públicos e internet | C62: Energia y alumbrado publico | D62: ICE | E62: Tarjeta | F62: =89350/459 -> 194.66231 | G62: 75751
A63: 46309 | B63: Mantenimiento y reparaciones | C63: Materiales de Construccion | D63: Grupo Materiales | E63: Tarjeta | F63: =787831.4/459 -> 1716.4083 | G63: 23899
A64: 46309 | B64: Mantenimiento y reparaciones | C64: Materiales de Construccion | D64: Grupo Materiales | E64: Tarjeta | F64: =677797.48/459 -> 1476.683 | G64: 23898
A65: 46309 | B65: Mantenimiento y reparaciones | C65: Materiales de Construccion | D65: Grupo Materiales | E65: Tarjeta | F65: =14212.57/459 -> 30.964205 | G65: 23900
A66: 46309 | B66: Mantenimiento y reparaciones | C66: Materiales de Construccion | D66: Grupo Materiales | E66: Tarjeta | F66: =280383.48/459 -> 610.85725 | G66: 23904
A67: 46309 | B67: Suministros y amenities | C67: Gas | D67: Vio Gas | E67: Transferencia / SINPE | F67: =150612/459 -> 328.13072 | G67: 10972
A68: 46309 | B68: Imprevistos y otros | C68: Taller Mecanico | D68: Ana Lorena | E68: Transferencia / SINPE | F68: =209812.75/459 -> 457.10839 | G68: 66
A69: 46309 | B69: Imprevistos y otros | C69: Taller Mecanico | D69: Ana Lorena | E69: Transferencia / SINPE | F69: =209812.75/459 -> 457.10839 | G69: 3
A70: 46309 | B70: Imprevistos y otros | C70: Taller Mecanico | D70: Ana Lorena | E70: Transferencia / SINPE | F70: =209812.75/459 -> 457.10839 | G70: 67
A71: 46309 | B71: Alimentos y bebidas | C71: Gastos de representacion | D71: SIBU | E71: Tarjeta | F71: =3288.82/459 -> 7.1651852 | G71: 408
A72: 46309 | B72: Servicios públicos e internet | C72: Energia y alumbrado publico | D72: ICE | E72: Tarjeta | F72: =107390/459 -> 233.96514 | G72: 75767
A73: 46309 | B73: Alimentos y bebidas | C73: Gastos de representacion | D73: Mosaic | E73: Efectivo | F73: =56430/459 -> 122.94118 | G73: 90990
A74: 46309 | B74: Servicios públicos e internet | C74: Energia y alumbrado publico | D74: ICE | E74: Tarjeta | F74: =142750/459 -> 311.00218 | G74: 75798
A75: 46309 | B75: Servicios públicos e internet | C75: Energia y alumbrado publico | D75: ICE | E75: Tarjeta | F75: =38175/459 -> 83.169935 | G75: 75664
A76: 46309 | B76: Alimentos y bebidas | C76: Gastos de representacion | D76: Mosaic | E76: Tarjeta | F76: =56430/459 -> 122.94118 | G76: 69220
A77: 46310 | B77: Nómina y salarios | C77: Pago IQ Octubre | D77: Canavida | E77: Transferencia / SINPE | F77: 8000 | G77: 100
A78: 46310 | B78: Servicios públicos e internet | C78: Plan Celular | D78: ICE | E78: Tarjeta | F78: =12740.71/459 -> 27.757538 | G78: 2769
A79: 46310 | B79: Mantenimiento y reparaciones | C79: Materiales de Construccion | D79: Grupo Materiales | E79: Transferencia / SINPE | F79: =719719.63/459 -> 1568.0166 | G79: 5041
A80: 46310 | B80: Mantenimiento y reparaciones | C80: Materiales de Construccion | D80: Colono | E80: Tarjeta | F80: =145175.08/459 -> 316.28558 | G80: 48418
A81: 46310 | B81: Comisiones de plataformas | C81: Pago de Booking | D81: Booking | E81: Tarjeta | F81: 2824.59 | G81: 321547
A82: 46311 | B82: Mantenimiento y reparaciones | C82: Materiales de Construccion | D82: Grupo Materiales | E82: Transferencia / SINPE | F82: =221122.45/459 -> 481.74826 | G82: 24013
A83: 46311 | B83: Combustible y transporte | C83: Gasolina | D83: GS La Colonia | E83: Tarjeta | F83: =186522/459 -> 406.36601 | G83: 53007
A84: 46311 | B84: Mantenimiento y reparaciones | C84: Materiales de Construccion | D84: Colono | E84: Tarjeta | F84: =110247.07/459 -> 240.1897 | G84: 8442
A85: 46311 | B85: Alimentos y bebidas | C85: Gastos de representacion | D85: Al Chile que si | E85: Tarjeta | F85: =8815/459 -> 19.204793 | G85: 2603
A86: 46311 | B86: Imprevistos y otros | C86: Repuestos de moto | D86: Repuestos Ramirez | E86: Tarjeta | F86: =20502.72/459 -> 44.668235 | G86: 555
A87: 46311 | B87: Mantenimiento y reparaciones | C87: Repuesto Lavadora | D87: Repuestos Uvita | E87: Tarjeta | F87: =90200/459 -> 196.51416 | G87: 457
A88: 46311 | B88: Alimentos y bebidas | C88: Gastos de representacion | D88: La Lico Happy Point | E88: Tarjeta | F88: =2750/459 -> 5.9912854 | G88: 6448
A89: 46311 | B89: Limpieza y lavandería | C89: Suministros Lavanderia | D89: Natural Cleaner | E89: Transferencia / SINPE | F89: =212440/459 -> 462.83224 | G89: 2370
A90: 46311 | B90: Alimentos y bebidas | C90: PEdido para alimentacion empleados | D90: BM Supermercado | E90: Tarjeta | F90: =5482.35/459 -> 11.944118 | G90: 4567
A91: 46312 | B91: Imprevistos y otros | C91: Contabilidad Servicios | D91: CR Contadores | E91: Transferencia / SINPE | F91: 244.5 | G91: 44837
A92: 46312 | B92: Alimentos y bebidas | C92: Gastos de representacion | D92: La Fogata | E92: Tarjeta | F92: =52202/459 -> 113.72985 | G92: 1531
A93: 46312 | B93: Alimentos y bebidas | C93: Gastos de representacion | D93: Vive Uvita | E93: Tarjeta | F93: =31800/459 -> 69.281046 | G93: 1532
A94: 46312 | B94: Imprevistos y otros | C94: Servicios Contables | D94: CR Contadores | E94: Transferencia / SINPE | F94: 244.5 | G94: 4837
A95: 46313 | B95: Software y tecnología | C95: Membresia | D95: Pricelabs | E95: Tarjeta | F95: 132.84 | G95: 884
A96: 46313 | B96: Alimentos y bebidas | C96: Pedido para alimentacion empleados | D96: BM Supermercado | E96: Transferencia / SINPE | F96: =10568/459 -> 23.023965 | G96: 4567
A97: 46314 | B97: Alimentos y bebidas | C97: Pedido para alimentacion empleados | D97: Frutas y Verduras Generaleñas | E97: Transferencia / SINPE | F97: =67515/459 -> 147.0915 | G97: 1183
A98: 46314 | B98: Alimentos y bebidas | C98: Pedido para alimentacion empleados | D98: BM Supermercado | E98: Transferencia / SINPE | F98: =96468/459 -> 210.16993 | G98: 4567
A99: 46314 | B99: Suministros y amenities | C99: Suministros Lavanderia | D99: Natural Cleaner | E99: Transferencia / SINPE | F99: =61585/459 -> 134.17211 | G99: 3013
A100: 46314 | B100: Jardinería y piscinas | C100: Suministro JArdineria | D100: Boticas Alfaro | E100: Tarjeta | F100: =11875/459 -> 25.87146 | G100: 4735
...

Sheet Ingresos Diarios
A1: Registro de Ingresos Diarios
A2: Una fila por ingreso desde la fila 6 (celdas en azul). Para hospedaje anote las noches vendidas (1 por villa por noche si registra día a día). Columna H: cómo se cobró (si fue en Efectivo, anótelo también en la hoja Caja Efectivo).
A3: 46300 | D3: Reserva #1024 – Familia Tremblay | E3: Airbnb | F3: 1 | H3: 320 | I3: Tarjeta | J3: ← Ejemplo (no se suma; puede borrarlo)
A4: Registros: | B4: =COUNT(A27:A1026) -> 96 | E4: Total noches | monto: | F4: =SUM(F27:F1026) -> 166 | H4: =SUM(H6:H200) -> 28669.381
A5: Fecha | B5: Villa / unidad | C5: Categoría | D5: Huésped / Reserva | E5: Canal | F5: Noches vendidas | G5: Email | H5: Monto (USD) | I5: Método de cobro
A6: 46296 | C6: Hospedaje | E6: Booking.com | H6: 92 | I6: Tarjeta
A7: 46296 | C7: Hospedaje | E7: Airbnb | H7: 613 | I7: Tarjeta
A8: 46297 | C8: Hospedaje | E8: Airbnb | H8: 1500 | I8: Tarjeta
A9: 46297 | C9: Hospedaje | E9: Booking.com | H9: 1010 | I9: Tarjeta
A10: 46297 | C10: Hospedaje | E10: Expedia | H10: 381 | I10: Tarjeta
A11: 46298 | C11: Hospedaje | E11: Airbnb | H11: 739 | I11: Tarjeta
A12: 46298 | C12: Hospedaje | E12: Expedia | H12: 593 | I12: Tarjeta
A13: 46299 | C13: Hospedaje | E13: Airbnb | H13: 663 | I13: Tarjeta
A14: 46299 | C14: Hospedaje | E14: Booking.com | H14: 218 | I14: Tarjeta
A15: 46300 | C15: Hospedaje | E15: Airbnb | H15: 279 | I15: Tarjeta
A16: 46300 | C16: Hospedaje | E16: Booking.com | H16: 124 | I16: Tarjeta
A17: 46301 | C17: Hospedaje | E17: Web (Lodgify) | H17: 401 | I17: Tarjeta
... A26: 46305 | C26: Hospedaje | E26: Booking.com | H26: 545 | I26: Tarjeta
A27: 46306 | B27: Colibri | C27: Hospedaje | D27: Carline Kross | E27: Airbnb | F27: 2 | H27: 372.9 | I27: Transferencia / SINPE
A28: 46306 | B28: Iguana (Condo 2) | C28: Hospedaje | D28: Philipp Egbers | E28: Booking.com | F28: 3 | H28: 160.6 | I28: Tarjeta
A29: 46306 | B29: Toucan (3 hab) | C29: Hospedaje | D29: Mik van der Drift | E29: Booking.com | F29: 3 | H29: 321.65 | I29: Tarjeta
A30: 46306 | B30: Lizardo (Condo 5) | C30: Hospedaje | D30: Britt Reinke | E30: Booking.com | F30: 2 | H30: 121.84 | I30: Tarjeta
A31: 46306 | B31: Rana (Condo 6) | C31: Hospedaje | D31: Monica Perez | E31: Booking.com | F31: 1 | H31: 115.42 | I31: Tarjeta
A32: 46306 | B32: Caracara (2 hab) | C32: Hospedaje | D32: Franci Zell | E32: Booking.com | F32: 3 | H32: 429.09 | I32: Tarjeta
A33: 46306 | B33: Torogoz (4 hab) | C33: Hospedaje | D33: Fabio Rivera | E33: Directo / WhatsApp | F33: 1 | H33: 155 | I33: Transferencia / SINPE
A34: 46306 | B34: Tortuga | C34: Early/Late Check Out | D34: Daniel Gonzalez | E34: Directo / WhatsApp | F34: 1 | H34: 75 | I34: Transferencia / SINPE
A35: 46306 | B35: Colibri | C35: Early/Late Check Out | D35: Carline Kross | E35: Airbnb | F35: 2 | H35: 21 | I35: Efectivo
A36: 46307 | B36: Quetzal (4 hab) | C36: Hospedaje | D36: Richard Ventura | E36: Expedia | F36: 3 | H36: 270.25 | I36: Tarjeta
A37: 46307 | B37: Lapa (3 hab) | C37: Hospedaje | D37: Pavla Muller | E37: Booking.com | F37: 3 | H37: 274.88 | I37: Tarjeta
A38: 46308 | B38: Torogoz (4 hab) | C38: Hospedaje | D38: Referidos Chris | E38: Directo / WhatsApp | F38: 1 | H38: 180 | I38: Transferencia / SINPE
... A49: 46310 | B49: Toucan (3 hab) | C49: Hospedaje | D49: Mariam Berrocal | E49: Directo / WhatsApp | F49: 2 | H49: 168.84 | I49: Transferencia / SINPE
A50: 46310 | B50: Toucan (3 hab) | C50: Hospedaje | D50: Mariam Berrocal | E50: Directo / WhatsApp | F50: 2 | H50: =10000/459 -> 21.786492 | I50: Transferencia / SINPE
A51: 46310 | B51: Lapa (3 hab) | C51: Hospedaje | D51: Shannel Beecher | E51: Booking.com | F51: 3 | H51: 403.58 | I51: Tarjeta
A52: 46310 | B52: Quetzal (4 hab) | C52: Hospedaje | D52: Barbera Muktem | E52: Booking.com | F52: 2 | H52: 191.06 | I52: Tarjeta
A53: 46310 | B53: Cusinga (1 hab) | C53: Hospedaje | D53: Kendall Vargas | E53: Airbnb | F53: 1 | H53: 135.74 | I53: Transferencia / SINPE
A54: 46310 | B54: Cusinga (1 hab) | C54: Hospedaje | D54: Kendall Vargas | E54: Airbnb | F54: 1 | H54: =10000/459 -> 21.786492 | I54: Transferencia / SINPE
A55: 46310 | B55: Colibri | C55: Hospedaje | D55: Nicole Mills | E55: Airbnb | F55: 1 | H55: 117.44 | I55: Tarjeta
A56: 46310 | B56: Recepcion | C56: Tours y actividades | D56: Tabla de Picar | E56: Directo / WhatsApp | F56: 0 | H56: 20 | I56: Tarjeta
A57: 46311 | B57: Torogoz (4 hab) | C57: Hospedaje | D57: Daniel Vergara | E57: Airbnb | F57: 1 | H57: 133.88 | I57: Tarjeta
A58: 46311 | B58: Torogoz (4 hab) | C58: Hospedaje | D58: Daniel Vergara | E58: Airbnb | F58: 1 | H58: =10000/459 -> 21.786492 | I58: Transferencia / SINPE
A59: 46311 | B59: Loro (4 hab) | C59: Hospedaje | D59: Jannet Vargas | E59: Expedia | F59: 2 | H59: 280.84 | I59: Tarjeta
A60: 46311 | B60: Gecko (Condo 3) | C60: Hospedaje | D60: Daniel Berrocal | E60: Airbnb | F60: 2 | H60: 140 | I60: Tarjeta
A61: 46311 | B61: Cusinga (1 hab) | C61: Hospedaje | D61: Cindy Torres | E61: Airbnb | F61: 2 | H61: 207.2 | I61: Tarjeta
A62: 46311 | B62: Caracara (2 hab) | C62: Hospedaje | D62: Wagner | E62: Directo / WhatsApp | F62: 1 | H62: 111 | I62: Tarjeta
A63: 46311 | B63: Lizardo (Condo 5) | C63: Hospedaje | D63: Barbera Muktem | E63: Directo / WhatsApp | F63: 1 | H63: 124 | I63: Efectivo
A64: 46311 | B64: Rana (Condo 6) | C64: Hospedaje | D64: Francinie Carvajal | E64: Airbnb | F64: 2 | H64: 208.93 | I64: Tarjeta
A65: 46311 | B65: Colibri | C65: Hospedaje | D65: Nicole Mills | E65: Directo / WhatsApp | F65: 1 | H65: 260 | I65: Efectivo
A66: 46312 | B66: Loro (4 hab) | C66: Cleaning Fee | D66: Jannet Vargas | E66: Expedia | F66: 2 | H66: 40 | I66: Efectivo
A67: 46312 | B67: Pavon | C67: Hospedaje | D67: Daniel Matarrita | E67: Booking.com | F67: 1 | H67: 140.31 | I67: Tarjeta
A68: 46312 | B68: Caracara (2 hab) | C68: Hospedaje | D68: Guirardo Serrano | E68: Booking.com | F68: 2 | H68: 217.65 | I68: Tarjeta
A69: 46312 | B69: Quetzal (4 hab) | C69: Hospedaje | D69: Patricia Rios | E69: Airbnb | F69: 1 | H69: 163.66 | I69: Tarjeta
A70: 46312 | B70: Torogoz (4 hab) | C70: Hospedaje | D70: Joseph Andres | E70: Airbnb | F70: 1 | H70: 253.33 | I70: Tarjeta
... A76: 46313 | B76: Lapa (3 hab) | C76: Hospedaje | D76: Leany Cunnigham | E76: Airbnb | F76: 3 | H76: 329.96 | I76: Tarjeta
A77: 46313 | B77: Colibri | C77: Hospedaje | D77: Allison Quiros | E77: Directo / WhatsApp | F77: 1 | H77: =65000/459 -> 141.6122 | I77: Tarjeta
A78: 46313 | B78: Quetzal (4 hab) | C78: Hospedaje | D78: Karen Cruz | E78: Directo / WhatsApp | F78: 1 | H78: =70000/459 -> 152.50545 | I78: Tarjeta
A79: 46313 | B79: Cusinga (1 hab) | C79: Hospedaje | D79: Maikol Solorzano | E79: Directo / WhatsApp | F79: 1 | H79: 152.51 | I79: Tarjeta
A80: 46313 | B80: Rana (Condo 6) | C80: Hospedaje | D80: Hayley Curran | E80: Airbnb | F80: 3 | H80: 235.2 | I80: Tarjeta
A81: 46313 | B81: Loro (4 hab) | C81: Hospedaje | D81: Kathya Mora | E81: Airbnb | F81: 1 | H81: =50000/459 -> 108.93246 | I81: Tarjeta
A82: 46313 | B82: Loro (4 hab) | C82: Hospedaje | D82: Jannet Vargas | E82: Expedia | F82: 2 | H82: =10000/459 -> 21.786492 | I82: Tarjeta
A83: 46313 | B83: Lizardo (Condo 5) | C83: Hospedaje | D83: Arnoldo | E83: Directo / WhatsApp | F83: 1 | H83: =35000/459 -> 76.252723 | I83: Tarjeta
A84: 46314 | B84: Caracara (2 hab) | C84: Hospedaje | D84: Dylan Barters | E84: Booking.com | F84: 2 | H84: 202.51 | I84: Tarjeta
A85: 46314 | B85: Iguana (Condo 2) | C85: Hospedaje | D85: Maricela Vargas | E85: Booking.com | F85: 3 | H85: 169.61 | I85: Tarjeta
A86: 46315 | B86: Loro (4 hab) | C86: Hospedaje | D86: Nicy Barrett | E86: Airbnb | F86: 2 | H86: 293.94 | I86: Tarjeta
A87: 46315 | B87: Quetzal (4 hab) | C87: Hospedaje | D87: Ariel Fernandez | E87: Airbnb | F87: 1 | H87: 153.68 | I87: Tarjeta
A88: 46315 | B88: Oropendola (2 hab) | C88: Hospedaje | D88: Grettel H | E88: Airbnb | F88: 2 | H88: 231.31 | I88: Tarjeta
A89: 46316 | B89: Quetzal (4 hab) | C89: Hospedaje | D89: Jeiry Pitty | E89: Airbnb | F89: 2 | H89: 757.1 | I89: Tarjeta
A90: 46316 | B90: Torogoz (4 hab) | C90: Hospedaje | D90: Ceciliano Blanco | E90: Booking.com | F90: 2 | H90: 269.44 | I90: Tarjeta
A91: 46316 | B91: Colibri | C91: Hospedaje | D91: Christian Peñaranda | E91: Directo / WhatsApp | F91: 2 | H91: 240 | I91: Transferencia / SINPE
A92: 46316 | B92: Cusinga (1 hab) | C92: Hospedaje | D92: Steffen Sellmeyer | E92: Booking.com | F92: 2 | H92: 242.74 | I92: Tarjeta
A93: 46316 | B93: Lizardo (Condo 5) | C93: Hospedaje | D93: Maria Jose Fonseca | E93: Directo / WhatsApp | F93: 2 | H93: 152 | I93: Transferencia / SINPE
A94: 46316 | B94: Iguana (Condo 2) | C94: Hospedaje | D94: Andrea Mora | E94: Booking.com | F94: 1 | H94: 127.62 | I94: Tarjeta
A95: 46316 | B95: Lizardo (Condo 5) | C95: Early/Late Check Out | D95: Maria Jose Fonseca | E95: Directo / WhatsApp | F95: 2 | H95: =5000/459 -> 10.893246 | I95: Efectivo
A96: 46316 | B96: Quetzal (4 hab) | C96: Mascota | D96: Jeiry Pitty | E96: Airbnb | F96: 2 | H96: =20000/459 -> 43.572985 | I96: Transferencia / SINPE
A97: 46317 | B97: Rana (Condo 6) | C97: Hospedaje | D97: Alicia Picado | E97: Booking.com | F97: 1 | H97: 92.23 | I97: Tarjeta
A98: 46317 | B98: Caracara (2 hab) | C98: Hospedaje | D98: Carlos Monge | E98: Airbnb | F98: 3 | H98: 457.09 | I98: Tarjeta
A99: 46317 | B99: Loro (4 hab) | C99: Hospedaje | D99: Daniela Sanchez | E99: Airbnb | F99: 2 | H99: 287.16 | I99: Tarjeta
A100: 46317 | B100: Toucan (3 hab) | C100: Hospedaje | D100: Emanuel Vargas | E100: Airbnb | F100: 1 | H100: 150.29 | I100: Tarjeta
A101: 46317 | B101: Oropendola (2 hab) | C101: Hospedaje | D101: Alejandro Barquero | E101: Airbnb | F101: 2 | H101: 264.87 | I101: Tarjeta
A102: 46317 | B102: Tortuga | C102: Hospedaje | D102: Uvita Print | E102: Directo / WhatsApp | F102: 1 | H102: 125 | I102: Tarjeta
A103: 46318 | B103: Lapa (3 hab) | C103: Hospedaje | D103: Lauren Marin | E103: Airbnb | F103: 2 | H103: 297.19 | I103: Tarjeta
A104: 46318 | B104: Lapa (3 hab) | C104: Early/Late Check Out | D104: Lauren Marin | E104: Airbnb | F104: 2 | H104: =10000/459 -> 21.786492 | I104: Transferencia / SINPE
A105: 46318 | B105: Quetzal (4 hab) | C105: Hospedaje | D105: Laurence Calderon | E105: Airbnb | F105: 1 | H105: 160.46 | I105: Tarjeta
A106: 46318 | B106: Toucan (3 hab) | C106: Hospedaje | D106: ⁨Melissa Rivera | E106: Airbnb | F106: 2 | H106: 277.08 | I106: Tarjeta
A107: 46318 | B107: Rana (Condo 6) | C107: Hospedaje | D107: Nazareth Chacon | E107: Directo / WhatsApp | F107: 1 | H107: =109000/459 -> 237.47277 | I107: Tarjeta
A108: 46318 | B108: Iguana (Condo 2) | C108: Hospedaje | D108: Gaboury Guillaume | E108: Booking.com | F108: 2 | H108: 156.66 | I108: Tarjeta
A109: 46319 | B109: Loro (4 hab) | C109: Hospedaje | D109: Eduardo Rodríguez | E109: Booking.com | F109: 2 | H109: 383.17 | I109: Tarjeta
A110: 46319 | B110: Torogoz (4 hab) | C110: Hospedaje | D110: Marianna Nikole | E110: Airbnb | F110: 1 | H110: 202.5 | I110: Tarjeta
A111: 46319 | B111: Oropendola (2 hab) | C111: Hospedaje | D111: Deibys Prado | E111: Airbnb | F111: 1 | H111: 148.03 | I111: Tarjeta
A112: 46319 | B112: Cusinga (1 hab) | C112: Hospedaje | D112: Erick Gómez Masís | E112: Airbnb | F112: 1 | H112: 133.34 | I112: Tarjeta
A113: 46319 | B113: Toucan (3 hab) | C113: Mascota | D113: ⁨Melissa Rivera | E113: Airbnb | F113: 2 | H113: 20 | I113: Efectivo
A114: 46319 | B114: Quetzal (4 hab) | C114: Mascota | D114: Kevin Gonzalez | E114: Directo / WhatsApp | F114: 2 | H114: 50 | I114: Transferencia / SINPE
A115: 46320 | B115: Oropendola (2 hab) | C115: Hospedaje | D115: Cinthia Leandro | E115: Airbnb | F115: 1 | H115: 135.6 | I115: Tarjeta
A116: 46320 | B116: Lizardo (Condo 5) | C116: Hospedaje | D116: Evan Robinson | E116: Expedia | F116: 2 | H116: 68.02 | I116: Tarjeta
A117: 46320 | B117: Salamandra (Condo 4) | C117: Hospedaje | D117: Maria Vitória Santos | E117: Expedia | F117: 3 | H117: 197.06 | I117: Tarjeta
A118: 46320 | B118: Rana (Condo 6) | C118: Hospedaje | D118: Enoch Verdon | E118: Airbnb | F118: 3 | H118: 308 | I118: Tarjeta
A119: 46320 | B119: Iguana (Condo 2) | C119: Hospedaje | D119: Carina Hanschke | E119: Booking.com | F119: 3 | H119: 319.78 | I119: Tarjeta
A120: 46320 | B120: Torogoz (4 hab) | C120: Early/Late Check Out | D120: Marianna Nikole | E120: Airbnb | F120: 1 | H120: =10000/459 -> 21.786492 | I120: Transferencia / SINPE
A121: 46320 | B121: Salamandra (Condo 4) | C121: Cleaning Fee | D121: Maria Vitória Santos | E121: Expedia | F121: 3 | H121: 30 | I121: Efectivo
A122: 46320 | B122: Lizardo (Condo 5) | C122: Cleaning Fee | D122: Evan Robinson | E122: Expedia | F122: 2 | H122: 30 | I122: Tarjeta

Sheet Caja Efectivo
A1: Caja Efectivo – Movimientos de Dinero en Efectivo
A2: Una fila por cada entrada o salida de efectivo desde la fila 6 (celdas en azul). Anote cada movimiento el mismo día, en orden, con su comprobante. Las ventas y compras en efectivo se registran TAMBIÉN en Ingresos Diarios o Gastos Diarios; los retiros y depósitos de banco solo aquí.
A3: 46300 | B3: Compra / pago en efectivo | C3: Salida | D3: Compra de cloro para piscinas | E3: Jardinería y piscinas | F3: Toucan (3 hab) | G3: Mantenimiento | H3: Fact. 0012346 | I3: CRC | J3: 25000 | K3: 510 | L3: 49.019608 | M3: ← Ejemplo (no se suma; puede borrarlo)
A4: Registros: | B4: =COUNT(A6:A1005) -> 9 | K4: Saldo actual:
A5: Fecha | B5: Tipo de movimiento | C5: Dirección | D5: Descripción | E5: Categoría | F5: Villa / unidad | G5: Responsable | H5: Comprobante / factura | I5: Moneda | J5: Monto | K5: Tipo de cambio (₡ por $) | L5: Monto en USD | M5: Notas
A6: 46306 | B6: Venta / cobro en efectivo | C6: {=IF(B6="","",IFERROR(INDEX(Listas!$Q$5:$Q$20,MATCH(B6,Listas!$P$5:$P$20,0)),""))} -> Entrada | D6: Pago en efectivo dolares | E6: Extra Guest Fee | F6: Colibri | G6: Carlos | H6: WA Grupo | I6: USD | J6: 21 | K6: 430 | L6: =IF(OR(J6="",I6=""),"",IF(I6="USD",J6,IF(N(K6)=0,"",J6/K6))) -> 21
A7: 46308 | B7: Venta / cobro en efectivo | C7: {=IF(B7="","",IFERROR(INDEX(Listas!$Q$5:$Q$20,MATCH(B7,Listas!$P$5:$P$20,0)),""))} -> Entrada | D7: Pago en efectivo dolares | E7: Limpieza y lavandería | F7: Quetzal (4 hab) | G7: Carlos | H7: Oficina | I7: USD | J7: 30 | K7: 430 | L7: =IF(OR(J7="",I7=""),"",IF(I7="USD",J7,IF(N(K7)=0,"",J7/K7))) -> 30
A8: 46309 | B8: Venta / cobro en efectivo | C8: {=IF(B8="","",IFERROR(INDEX(Listas!$Q$5:$Q$20,MATCH(B8,Listas!$P$5:$P$20,0)),""))} -> Entrada | D8: Pago en Euros | E8: Hospedaje | F8: Rana (Condo 6) | G8: Carlos | H8: Jess | I8: USD | J8: 108 | K8: 430 | L8: =IF(OR(J8="",I8=""),"",IF(I8="USD",J8,IF(N(K8)=0,"",J8/K8))) -> 108
A9: 46311 | B9: Venta / cobro en efectivo | C9: {=IF(B9="","",IFERROR(INDEX(Listas!$Q$5:$Q$20,MATCH(B9,Listas!$P$5:$P$20,0)),""))} -> Entrada | D9: Extra Noche | E9: Hospedaje | F9: Colibri | G9: Carlos | H9: Carlos | I9: USD | J9: 260 | K9: 459 | L9: =IF(OR(J9="",I9=""),"",IF(I9="USD",J9,IF(N(K9)=0,"",J9/K9))) -> 260
A10: 46311 | B10: Venta / cobro en efectivo | C10: {=IF(B10="","",IFERROR(INDEX(Listas!$Q$5:$Q$20,MATCH(B10,Listas!$P$5:$P$20,0)),""))} -> Entrada | D10: Extra Noche | E10: Hospedaje | F10: Lizardo (Condo 5) | G10: Carlos | H10: Carlos | I10: USD | J10: 124 | K10: 459 | L10: =IF(OR(J10="",I10=""),"",IF(I10="USD",J10,IF(N(K10)=0,"",J10/K10))) -> 124
A11: 46312 | B11: Venta / cobro en efectivo | C11: {=IF(B11="","",IFERROR(INDEX(Listas!$Q$5:$Q$20,MATCH(B11,Listas!$P$5:$P$20,0)),""))} -> Entrada | D11: Cleaning Fee | E11: Limpieza y lavandería | F11: Lapa (3 hab) | G11: Carlos | H11: Carlos | I11: USD | J11: 40 | K11: 459 | L11: =IF(OR(J11="",I11=""),"",IF(I11="USD",J11,IF(N(K11)=0,"",J11/K11))) -> 40
A12: 46313 | B12: Venta / cobro en efectivo | C12: {=IF(B12="","",IFERROR(INDEX(Listas!$Q$5:$Q$20,MATCH(B12,Listas!$P$5:$P$20,0)),""))} -> Entrada | D12: Pyrex roto | E12: Imprevistos y otros | F12: Loro (4 hab) | G12: Carlos | H12: Carlos | I12: USD | J12: =10000/459 -> 21.786492 | K12: 459 | L12: =IF(OR(J12="",I12=""),"",IF(I12="USD",J12,IF(N(K12)=0,"",J12/K12))) -> 21.786492
A13: 46319 | B13: Venta / cobro en efectivo | C13: {=IF(B13="","",IFERROR(INDEX(Listas!$Q$5:$Q$20,MATCH(B13,Listas!$P$5:$P$20,0)),""))} -> Entrada | D13: Mascota | E13: Mascota | F13: Quetzal (4 hab) | G13: Carlos | H13: Carlos | I13: USD | J13: 20 | K13: 459 | L13: =IF(OR(J13="",I13=""),"",IF(I13="USD",J13,IF(N(K13)=0,"",J13/K13))) -> 20
A14: 46320 | B14: Venta / cobro en efectivo | C14: {=IF(B14="","",IFERROR(INDEX(Listas!$Q$5:$Q$20,MATCH(B14,Listas!$P$5:$P$20,0)),""))} -> Entrada | D14: Cleaning Fee | E14: Limpieza y lavandería | F14: Salamandra (Condo 4) | G14: Carlos | H14: Carlos | I14: USD | J14: 30 | K14: 459 | L14: =IF(OR(J14="",I14=""),"",IF(I14="USD",J14,IF(N(K14)=0,"",J14/K14))) -> 30
C15: {=IF(B15="","",IFERROR(INDEX(Listas!$Q$5:$Q$20,MATCH(B15,Listas!$P$5:$P$20,0)),""))} | L15: =IF(OR(J15="",I15=""),"",IF(I15="USD",J15,IF(N(K15)=0,"",J15/K15)))
C16: {=IF(B16="","",IFERROR(INDEX(Listas!$Q$5:$Q$20,MATCH(B16,Listas!$P$5:$P$20,0)),""))} | L16: =IF(OR(J16="",I16=""),"",IF(I16="USD",J16,IF(N(K16)=0,"",J16/K16)))
C17: {=IF(B17="","",IFERROR(INDEX(Listas!$Q$5:$Q$20,MATCH(B17,Listas!$P$5:$P$20,0)),""))} | L17: =IF(OR(J17="",I17=""),"",IF(I17="USD",J17,IF(N(K17)=0,"",J17/K17)))
C18: {=IF(B18="","",IFERROR(INDEX(Listas!$Q$5:$Q$20,MATCH(B18,Listas!$P$5:$P$20,0)),""))} | L18: =IF(OR(J18="",I18=""),"",IF(I18="USD",J18,IF(N(K18)=0,"",J18/K18)))
C19: {=IF(B19="","",IFERROR(INDEX(Listas!$Q$5:$Q$20,MATCH(B19,Listas!$P$5:$P$20,0)),""))} | L19: =IF(OR(J19="",I19=""),"",IF(I19="USD",J19,IF(N(K19)=0,"",J19/K19)))
C20: {=IF(B20="","",IFERROR(INDEX(Listas!$Q$5:$Q$20,MATCH(B20,Listas!$P$5:$P$20,0)),""))} | L20: =IF(OR(J20="",I20=""),"",IF(I20="USD",J20,IF(N(K20)=0,"",J20/K20)))
C21: {=IF(B21="","",IFERROR(INDEX(Listas!$Q$5:$Q$20,MATCH(B21,Listas!$P$5:$P$20,0)),""))} | L21: =IF(OR(J21="",I21=""),"",IF(I21="USD",J21,IF(N(K21)=0,"",J21/K21)))
C22: {=IF(B22="","",IFERROR(INDEX(Listas!$Q$5:$Q$20,MATCH(B22,Listas!$P$5:$P$20,0)),""))} | L22: =IF(OR(J22="",I22=""),"",IF(I22="USD",J22,IF(N(K22)=0,"",J22/K22)))
C23: {=IF(B23="","",IFERROR(INDEX(Listas!$Q$5:$Q$20,MATCH(B23,Listas!$P$5:$P$20,0)),""))} | L23: =IF(OR(J23="",I23=""),"",IF(I23="USD",J23,IF(N(K23)=0,"",J23/K23)))
C24: {=IF(B24="","",IFERROR(INDEX(Listas!$Q$5:$Q$20,MATCH(B24,Listas!$P$5:$P$20,0)),""))} | L24: =IF(OR(J24="",I24=""),"",IF(I24="USD",J24,IF(N(K24)=0,"",J24/K24)))
C25: {=IF(B25="","",IFERROR(INDEX(Listas!$Q$5:$Q$20,MATCH(B25,Listas!$P$5:$P$20,0)),""))} | L25: =IF(OR(J25="",I25=""),"",IF(I25="USD",J25,IF(N(K25)=0,"",J25/K25)))
C26: {=IF(B26="","",IFERROR(INDEX(Listas!$Q$5:$Q$20,MATCH(B26,Listas!$P$5:$P$20,0)),""))} | L26: =IF(OR(J26="",I26=""),"",IF(I26="USD",J26,IF(N(K26)=0,"",J26/K26)))
... C1005: {=IF(B1005="","",IFERROR(INDEX(Listas!$Q$5:$Q$20,MATCH(B1005,Listas!$P$5:$P$20,0)),""))} | L1005: =IF(OR(J1005="",I1005=""),"",IF(I1005="USD",J1005,IF(N(K1005)=0,"",J1005/K1005)))

Sheet Arqueo y Resumen Caja
A1: Arqueo y Resumen de Caja
A2: Saldo inicial, flujo de efectivo por mes, conciliación con los registros diarios y arqueos (conteo físico del dinero). Celdas amarillas/azules = datos que usted llena.
A4: A. SALDO DE CAJA
A5: Concepto | B5: Fecha | C5: Monto
A6: Saldo inicial de caja USD | B6: =Listas!$L$5 -> 46300 | C6: 0 | D6: ← Cuente el efectivo real al iniciar y anótelo aquí
A7: Saldo inicial de caja colones (₡) | B7: =Listas!$L$5 -> 46300 | C7: 0
A9: Tipo de cambio para el total (₡ por $) | D9: ← Opcional: tipo de cambio del día para ver el total en USD
A11: Saldo actual en caja | D11: USD ($) | E11: Colones (₡) | F11: Total en USD*
A12: Saldo actual en caja (según registros) | D12: =C6+SUMIFS('Caja Efectivo'!$J$6:$J$1005,'Caja Efectivo'!$I$6:$I$1005,"USD",'Caja Efectivo'!$C$6:$C$1005,"Entrada")-SUMIFS('Caja Efectivo'!$J$6:$J$1005,'Caja Efectivo'!$I$6:$I$1005,"USD",'Caja Efectivo'!$C$6:$C$1005,"Salida") -> 654.78649 | E12: =C7+SUMIFS('Caja Efectivo'!$J$6:$J$1005,'Caja Efectivo'!$I$6:$I$1005,"CRC",'Caja Efectivo'!$C$6:$C$1005,"Entrada")-SUMIFS('Caja Efectivo'!$J$6:$J$1005,'Caja Efectivo'!$I$6:$I$1005,"CRC",'Caja Efectivo'!$C$6:$C$1005,"Salida") -> 0 | F12: =IF(N(C9)=0,D12,D12+E12/C9) -> 654.78649
A13: *Total en USD suma los colones convertidos con el tipo de cambio de C9 (si está vacío, solo muestra los dólares).
A15: B. FLUJO DE EFECTIVO POR MES
A16: Caja en dólares (USD) | B16: =Listas!$K$5 -> Octubre 2026 | C16: =Listas!$K$6 -> Noviembre 2026 | D16: =Listas!$K$7 -> Diciembre 2026 | E16: Total periodo
A17: Saldo inicial del mes | B17: =$C$6 -> 0 | C17: =B29 -> 654.78649 | D17: =C29 -> 654.78649 | E17: =B17 -> 0
A18: Venta / cobro en efectivo | B18: =SUMIFS('Caja Efectivo'!$J$6:$J$1005,'Caja Efectivo'!$B$6:$B$1005,"Venta / cobro en efectivo",'Caja Efectivo'!$A$6:$A$1005,">="&Listas!$L$5,'Caja Efectivo'!$A$6:$A$1005,"<="&Listas!$M$5,'Caja Efectivo'!$I$6:$I$1005,"USD") -> 654.78649 | C18: =SUMIFS('Caja Efectivo'!$J$6:$J$1005,'Caja Efectivo'!$B$6:$B$1005,"Venta / cobro en efectivo",'Caja Efectivo'!$A$6:$A$1005,">="&Listas!$L$6,'Caja Efectivo'!$A$6:$A$1005,"<="&Listas!$M$6,'Caja Efectivo'!$I$6:$I$1005,"USD") -> 0 | D18: =SUMIFS('Caja Efectivo'!$J$6:$J$1005,'Caja Efectivo'!$B$6:$B$1005,"Venta / cobro en efectivo",'Caja Efectivo'!$A$6:$A$1005,">="&Listas!$L$7,'Caja Efectivo'!$A$6:$A$1005,"<="&Listas!$M$7,'Caja Efectivo'!$I$6:$I$1005,"USD") -> 0 | E18: =SUM(B18:D18) -> 654.78649
A19: Retiro de banco a caja | B19: =SUMIFS('Caja Efectivo'!$J$6:$J$1005,'Caja Efectivo'!$B$6:$B$1005,"Retiro de banco a caja",'Caja Efectivo'!$A$6:$A$1005,">="&Listas!$L$5,'Caja Efectivo'!$A$6:$A$1005,"<="&Listas!$M$5,'Caja Efectivo'!$I$6:$I$1005,"USD") -> 0 | C19: =SUMIFS('Caja Efectivo'!$J$6:$J$1005,'Caja Efectivo'!$B$6:$B$1005,"Retiro de banco a caja",'Caja Efectivo'!$A$6:$A$1005,">="&Listas!$L$6,'Caja Efectivo'!$A$6:$A$1005,"<="&Listas!$M$6,'Caja Efectivo'!$I$6:$I$1005,"USD") -> 0 | D19: =SUMIFS('Caja Efectivo'!$J$6:$J$1005,'Caja Efectivo'!$B$6:$B$1005,"Retiro de banco a caja",'Caja Efectivo'!$A$6:$A$1005,">="&Listas!$L$7,'Caja Efectivo'!$A$6:$A$1005,"<="&Listas!$M$7,'Caja Efectivo'!$I$6:$I$1005,"USD") -> 0 | E19: =SUM(B19:D19) -> 0
A20: Otra entrada de efectivo | B20: =SUMIFS('Caja Efectivo'!$J$6:$J$1005,'Caja Efectivo'!$B$6:$B$1005,"Otra entrada de efectivo",'Caja Efectivo'!$A$6:$A$1005,">="&Listas!$L$5,'Caja Efectivo'!$A$6:$A$1005,"<="&Listas!$M$5,'Caja Efectivo'!$I$6:$I$1005,"USD") -> 0 | C20: =SUMIFS('Caja Efectivo'!$J$6:$J$1005,'Caja Efectivo'!$B$6:$B$1005,"Otra entrada de efectivo",'Caja Efectivo'!$A$6:$A$1005,">="&Listas!$L$6,'Caja Efectivo'!$A$6:$A$1005,"<="&Listas!$M$6,'Caja Efectivo'!$I$6:$I$1005,"USD") -> 0 | D20: =SUMIFS('Caja Efectivo'!$J$6:$J$1005,'Caja Efectivo'!$B$6:$B$1005,"Otra entrada de efectivo",'Caja Efectivo'!$A$6:$A$1005,">="&Listas!$L$7,'Caja Efectivo'!$A$6:$A$1005,"<="&Listas!$M$7,'Caja Efectivo'!$I$6:$I$1005,"USD") -> 0 | E20: =SUM(B20:D20) -> 0
A21: Ajuste de arqueo (+) | B21: =SUMIFS('Caja Efectivo'!$J$6:$J$1005,'Caja Efectivo'!$B$6:$B$1005,"Ajuste de arqueo (+)",'Caja Efectivo'!$A$6:$A$1005,">="&Listas!$L$5,'Caja Efectivo'!$A$6:$A$1005,"<="&Listas!$M$5,'Caja Efectivo'!$I$6:$I$1005,"USD") -> 0 | C21: =SUMIFS('Caja Efectivo'!$J$6:$J$1005,'Caja Efectivo'!$B$6:$B$1005,"Ajuste de arqueo (+)",'Caja Efectivo'!$A$6:$A$1005,">="&Listas!$L$6,'Caja Efectivo'!$A$6:$A$1005,"<="&Listas!$M$6,'Caja Efectivo'!$I$6:$I$1005,"USD") -> 0 | D21: =SUMIFS('Caja Efectivo'!$J$6:$J$1005,'Caja Efectivo'!$B$6:$B$1005,"Ajuste de arqueo (+)",'Caja Efectivo'!$A$6:$A$1005,">="&Listas!$L$7,'Caja Efectivo'!$A$6:$A$1005,"<="&Listas!$M$7,'Caja Efectivo'!$I$6:$I$1005,"USD") -> 0 | E21: =SUM(B21:D21) -> 0
A22: Total entradas | B22: =SUM(B18:B21) -> 654.78649 | C22: =SUM(C18:C21) -> 0 | D22: =SUM(D18:D21) -> 0 | E22: =SUM(B22:D22) -> 654.78649
A23: Compra / pago en efectivo | B23: =SUMIFS('Caja Efectivo'!$J$6:$J$1005,'Caja Efectivo'!$B$6:$B$1005,"Compra / pago en efectivo",'Caja Efectivo'!$A$6:$A$1005,">="&Listas!$L$5,'Caja Efectivo'!$A$6:$A$1005,"<="&Listas!$M$5,'Caja Efectivo'!$I$6:$I$1005,"USD") -> 0 | C23: =SUMIFS('Caja Efectivo'!$J$6:$J$1005,'Caja Efectivo'!$B$6:$B$1005,"Compra / pago en efectivo",'Caja Efectivo'!$A$6:$A$1005,">="&Listas!$L$6,'Caja Efectivo'!$A$6:$A$1005,"<="&Listas!$M$6,'Caja Efectivo'!$I$6:$I$1005,"USD") -> 0 | D23: =SUMIFS('Caja Efectivo'!$J$6:$J$1005,'Caja Efectivo'!$B$6:$B$1005,"Compra / pago en efectivo",'Caja Efectivo'!$A$6:$A$1005,">="&Listas!$L$7,'Caja Efectivo'!$A$6:$A$1005,"<="&Listas!$M$7,'Caja Efectivo'!$I$6:$I$1005,"USD") -> 0 | E23: =SUM(B23:D23) -> 0
A24: Depósito de caja al banco | B24: =SUMIFS('Caja Efectivo'!$J$6:$J$1005,'Caja Efectivo'!$B$6:$B$1005,"Depósito de caja al banco",'Caja Efectivo'!$A$6:$A$1005,">="&Listas!$L$5,'Caja Efectivo'!$A$6:$A$1005,"<="&Listas!$M$5,'Caja Efectivo'!$I$6:$I$1005,"USD") -> 0 | C24: =SUMIFS('Caja Efectivo'!$J$6:$J$1005,'Caja Efectivo'!$B$6:$B$1005,"Depósito de caja al banco",'Caja Efectivo'!$A$6:$A$1005,">="&Listas!$L$6,'Caja Efectivo'!$A$6:$A$1005,"<="&Listas!$M$6,'Caja Efectivo'!$I$6:$I$1005,"USD") -> 0 | D24: =SUMIFS('Caja Efectivo'!$J$6:$J$1005,'Caja Efectivo'!$B$6:$B$1005,"Depósito de caja al banco",'Caja Efectivo'!$A$6:$A$1005,">="&Listas!$L$7,'Caja Efectivo'!$A$6:$A$1005,"<="&Listas!$M$7,'Caja Efectivo'!$I$6:$I$1005,"USD") -> 0 | E24: =SUM(B24:D24) -> 0
A25: Vale / adelanto | B25: =SUMIFS('Caja Efectivo'!$J$6:$J$1005,'Caja Efectivo'!$B$6:$B$1005,"Vale / adelanto",'Caja Efectivo'!$A$6:$A$1005,">="&Listas!$L$5,'Caja Efectivo'!$A$6:$A$1005,"<="&Listas!$M$5,'Caja Efectivo'!$I$6:$I$1005,"USD") -> 0 | C25: =SUMIFS('Caja Efectivo'!$J$6:$J$1005,'Caja Efectivo'!$B$6:$B$1005,"Vale / adelanto",'Caja Efectivo'!$A$6:$A$1005,">="&Listas!$L$6,'Caja Efectivo'!$A$6:$A$1005,"<="&Listas!$M$6,'Caja Efectivo'!$I$6:$I$1005,"USD") -> 0 | D25: =SUMIFS('Caja Efectivo'!$J$6:$J$1005,'Caja Efectivo'!$B$6:$B$1005,"Vale / adelanto",'Caja Efectivo'!$A$6:$A$1005,">="&Listas!$L$7,'Caja Efectivo'!$A$6:$A$1005,"<="&Listas!$M$7,'Caja Efectivo'!$I$6:$I$1005,"USD") -> 0 | E25: =SUM(B25:D25) -> 0
A26: Ajuste de arqueo (−) | B26: =SUMIFS('Caja Efectivo'!$J$6:$J$1005,'Caja Efectivo'!$B$6:$B$1005,"Ajuste de arqueo (−)",'Caja Efectivo'!$A$6:$A$1005,">="&Listas!$L$5,'Caja Efectivo'!$A$6:$A$1005,"<="&Listas!$M$5,'Caja Efectivo'!$I$6:$I$1005,"USD") -> 0 | C26: =SUMIFS('Caja Efectivo'!$J$6:$J$1005,'Caja Efectivo'!$B$6:$B$1005,"Ajuste de arqueo (−)",'Caja Efectivo'!$A$6:$A$1005,">="&Listas!$L$6,'Caja Efectivo'!$A$6:$A$1005,"<="&Listas!$M$6,'Caja Efectivo'!$I$6:$I$1005,"USD") -> 0 | D26: =SUMIFS('Caja Efectivo'!$J$6:$J$1005,'Caja Efectivo'!$B$6:$B$1005,"Ajuste de arqueo (−)",'Caja Efectivo'!$A$6:$A$1005,">="&Listas!$L$7,'Caja Efectivo'!$A$6:$A$1005,"<="&Listas!$M$7,'Caja Efectivo'!$I$6:$I$1005,"USD") -> 0 | E26: =SUM(B26:D26) -> 0
A27: Total salidas | B27: =SUM(B23:B26) -> 0 | C27: =SUM(C23:C26) -> 0 | D27: =SUM(D23:D26) -> 0 | E27: =SUM(B27:D27) -> 0
A28: Flujo neto del mes | B28: =B22-B27 -> 654.78649 | C28: =C22-C27 -> 0 | D28: =D22-D27 -> 0 | E28: =SUM(B28:D28) -> 654.78649
A29: Saldo final del mes | B29: =B17+B28 -> 654.78649 | C29: =C17+C28 -> 654.78649 | D29: =D17+D28 -> 654.78649 | E29: =D29 -> 654.78649
A32: Caja en colones (₡) | B32: =Listas!$K$5 -> Octubre 2026 | C32: =Listas!$K$6 -> Noviembre 2026 | D32: =Listas!$K$7 -> Diciembre 2026 | E32: Total periodo
A33: Saldo inicial del mes | B33: =$C$7 -> 0 | C33: =B45 -> 0 | D33: =C45 -> 0 | E33: =B33 -> 0
A34: Venta / cobro en efectivo | B34: =SUMIFS('Caja Efectivo'!$J$6:$J$1005,'Caja Efectivo'!$B$6:$B$1005,"Venta / cobro en efectivo",'Caja Efectivo'!$A$6:$A$1005,">="&Listas!$L$5,'Caja Efectivo'!$A$6:$A$1005,"<="&Listas!$M$5,'Caja Efectivo'!$I$6:$I$1005,"CRC") -> 0 | C34: =SUMIFS('Caja Efectivo'!$J$6:$J$1005,'Caja Efectivo'!$B$6:$B$1005,"Venta / cobro en efectivo",'Caja Efectivo'!$A$6:$A$1005,">="&Listas!$L$6,'Caja Efectivo'!$A$6:$A$1005,"<="&Listas!$M$6,'Caja Efectivo'!$I$6:$I$1005,"CRC") -> 0 | D34: =SUMIFS('Caja Efectivo'!$J$6:$J$1005,'Caja Efectivo'!$B$6:$B$1005,"Venta / cobro en efectivo",'Caja Efectivo'!$A$6:$A$1005,">="&Listas!$L$7,'Caja Efectivo'!$A$6:$A$1005,"<="&Listas!$M$7,'Caja Efectivo'!$I$6:$I$1005,"CRC") -> 0 | E34: =SUM(B34:D34) -> 0
A35: Retiro de banco a caja | B35: =SUMIFS('Caja Efectivo'!$J$6:$J$1005,'Caja Efectivo'!$B$6:$B$1005,"Retiro de banco a caja",'Caja Efectivo'!$A$6:$A$1005,">="&Listas!$L$5,'Caja Efectivo'!$A$6:$A$1005,"<="&Listas!$M$5,'Caja Efectivo'!$I$6:$I$1005,"CRC") -> 0 | C35: =SUMIFS('Caja Efectivo'!$J$6:$J$1005,'Caja Efectivo'!$B$6:$B$1005,"Retiro de banco a caja",'Caja Efectivo'!$A$6:$A$1005,">="&Listas!$L$6,'Caja Efectivo'!$A$6:$A$1005,"<="&Listas!$M$6,'Caja Efectivo'!$I$6:$I$1005,"CRC") -> 0 | D35: =SUMIFS('Caja Efectivo'!$J$6:$J$1005,'Caja Efectivo'!$B$6:$B$1005,"Retiro de banco a caja",'Caja Efectivo'!$A$6:$A$1005,">="&Listas!$L$7,'Caja Efectivo'!$A$6:$A$1005,"<="&Listas!$M$7,'Caja Efectivo'!$I$6:$I$1005,"CRC") -> 0 | E35: =SUM(B35:D35) -> 0
A36: Otra entrada de efectivo | B36: =SUMIFS('Caja Efectivo'!$J$6:$J$1005,'Caja Efectivo'!$B$6:$B$1005,"Otra entrada de efectivo",'Caja Efectivo'!$A$6:$A$1005,">="&Listas!$L$5,'Caja Efectivo'!$A$6:$A$1005,"<="&Listas!$M$5,'Caja Efectivo'!$I$6:$I$1005,"CRC") -> 0 | C36: =SUMIFS('Caja Efectivo'!$J$6:$J$1005,'Caja Efectivo'!$B$6:$B$1005,"Otra entrada de efectivo",'Caja Efectivo'!$A$6:$A$1005,">="&Listas!$L$6,'Caja Efectivo'!$A$6:$A$1005,"<="&Listas!$M$6,'Caja Efectivo'!$I$6:$I$1005,"CRC") -> 0 | D36: =SUMIFS('Caja Efectivo'!$J$6:$J$1005,'Caja Efectivo'!$B$6:$B$1005,"Otra entrada de efectivo",'Caja Efectivo'!$A$6:$A$1005,">="&Listas!$L$7,'Caja Efectivo'!$A$6:$A$1005,"<="&Listas!$M$7,'Caja Efectivo'!$I$6:$I$1005,"CRC") -> 0 | E36: =SUM(B36:D36) -> 0
A37: Ajuste de arqueo (+) | B37: =SUMIFS('Caja Efectivo'!$J$6:$J$1005,'Caja Efectivo'!$B$6:$B$1005,"Ajuste de arqueo (+)",'Caja Efectivo'!$A$6:$A$1005,">="&Listas!$L$5,'Caja Efectivo'!$A$6:$A$1005,"<="&Listas!$M$5,'Caja Efectivo'!$I$6:$I$1005,"CRC") -> 0 | C37: =SUMIFS('Caja Efectivo'!$J$6:$J$1005,'Caja Efectivo'!$B$6:$B$1005,"Ajuste de arqueo (+)",'Caja Efectivo'!$A$6:$A$1005,">="&Listas!$L$6,'Caja Efectivo'!$A$6:$A$1005,"<="&Listas!$M$6,'Caja Efectivo'!$I$6:$I$1005,"CRC") -> 0 | D37: =SUMIFS('Caja Efectivo'!$J$6:$J$1005,'Caja Efectivo'!$B$6:$B$1005,"Ajuste de arqueo (+)",'Caja Efectivo'!$A$6:$A$1005,">="&Listas!$L$7,'Caja Efectivo'!$A$6:$A$1005,"<="&Listas!$M$7,'Caja Efectivo'!$I$6:$I$1005,"CRC") -> 0 | E37: =SUM(B37:D37) -> 0
A38: Total entradas | B38: =SUM(B34:B37) -> 0 | C38: =SUM(C34:C37) -> 0 | D38: =SUM(D34:D37) -> 0 | E38: =SUM(B38:D38) -> 0
A39: Compra / pago en efectivo | B39: =SUMIFS('Caja Efectivo'!$J$6:$J$1005,'Caja Efectivo'!$B$6:$B$1005,"Compra / pago en efectivo",'Caja Efectivo'!$A$6:$A$1005,">="&Listas!$L$5,'Caja Efectivo'!$A$6:$A$1005,"<="&Listas!$M$5,'Caja Efectivo'!$I$6:$I$1005,"CRC") -> 0 | C39: =SUMIFS('Caja Efectivo'!$J$6:$J$1005,'Caja Efectivo'!$B$6:$B$1005,"Compra / pago en efectivo",'Caja Efectivo'!$A$6:$A$1005,">="&Listas!$L$6,'Caja Efectivo'!$A$6:$A$1005,"<="&Listas!$M$6,'Caja Efectivo'!$I$6:$I$1005,"CRC") -> 0 | D39: =SUMIFS('Caja Efectivo'!$J$6:$J$1005,'Caja Efectivo'!$B$6:$B$1005,"Compra / pago en efectivo",'Caja Efectivo'!$A$6:$A$1005,">="&Listas!$L$7,'Caja Efectivo'!$A$6:$A$1005,"<="&Listas!$M$7,'Caja Efectivo'!$I$6:$I$1005,"CRC") -> 0 | E39: =SUM(B39:D39) -> 0
A40: Depósito de caja al banco | B40: =SUMIFS('Caja Efectivo'!$J$6:$J$1005,'Caja Efectivo'!$B$6:$B$1005,"Depósito de caja al banco",'Caja Efectivo'!$A$6:$A$1005,">="&Listas!$L$5,'Caja Efectivo'!$A$6:$A$1005,"<="&Listas!$M$5,'Caja Efectivo'!$I$6:$I$1005,"CRC") -> 0 | C40: =SUMIFS('Caja Efectivo'!$J$6:$J$1005,'Caja Efectivo'!$B$6:$B$1005,"Depósito de caja al banco",'Caja Efectivo'!$A$6:$A$1005,">="&Listas!$L$6,'Caja Efectivo'!$A$6:$A$1005,"<="&Listas!$M$6,'Caja Efectivo'!$I$6:$I$1005,"CRC") -> 0 | D40: =SUMIFS('Caja Efectivo'!$J$6:$J$1005,'Caja Efectivo'!$B$6:$B$1005,"Depósito de caja al banco",'Caja Efectivo'!$A$6:$A$1005,">="&Listas!$L$7,'Caja Efectivo'!$A$6:$A$1005,"<="&Listas!$M$7,'Caja Efectivo'!$I$6:$I$1005,"CRC") -> 0 | E40: =SUM(B40:D40) -> 0
A41: Vale / adelanto | B41: =SUMIFS('Caja Efectivo'!$J$6:$J$1005,'Caja Efectivo'!$B$6:$B$1005,"Vale / adelanto",'Caja Efectivo'!$A$6:$A$1005,">="&Listas!$L$5,'Caja Efectivo'!$A$6:$A$1005,"<="&Listas!$M$5,'Caja Efectivo'!$I$6:$I$1005,"CRC") -> 0 | C41: =SUMIFS('Caja Efectivo'!$J$6:$J$1005,'Caja Efectivo'!$B$6:$B$1005,"Vale / adelanto",'Caja Efectivo'!$A$6:$A$1005,">="&Listas!$L$6,'Caja Efectivo'!$A$6:$A$1005,"<="&Listas!$M$6,'Caja Efectivo'!$I$6:$I$1005,"CRC") -> 0 | D41: =SUMIFS('Caja Efectivo'!$J$6:$J$1005,'Caja Efectivo'!$B$6:$B$1005,"Vale / adelanto",'Caja Efectivo'!$A$6:$A$1005,">="&Listas!$L$7,'Caja Efectivo'!$A$6:$A$1005,"<="&Listas!$M$7,'Caja Efectivo'!$I$6:$I$1005,"CRC") -> 0 | E41: =SUM(B41:D41) -> 0
A42: Ajuste de arqueo (−) | B42: =SUMIFS('Caja Efectivo'!$J$6:$J$1005,'Caja Efectivo'!$B$6:$B$1005,"Ajuste de arqueo (−)",'Caja Efectivo'!$A$6:$A$1005,">="&Listas!$L$5,'Caja Efectivo'!$A$6:$A$1005,"<="&Listas!$M$5,'Caja Efectivo'!$I$6:$I$1005,"CRC") -> 0 | C42: =SUMIFS('Caja Efectivo'!$J$6:$J$1005,'Caja Efectivo'!$B$6:$B$1005,"Ajuste de arqueo (−)",'Caja Efectivo'!$A$6:$A$1005,">="&Listas!$L$6,'Caja Efectivo'!$A$6:$A$1005,"<="&Listas!$M$6,'Caja Efectivo'!$I$6:$I$1005,"CRC") -> 0 | D42: =SUMIFS('Caja Efectivo'!$J$6:$J$1005,'Caja Efectivo'!$B$6:$B$1005,"Ajuste de arqueo (−)",'Caja Efectivo'!$A$6:$A$1005,">="&Listas!$L$7,'Caja Efectivo'!$A$6:$A$1005,"<="&Listas!$M$7,'Caja Efectivo'!$I$6:$I$1005,"CRC") -> 0 | E42: =SUM(B42:D42) -> 0
A43: Total salidas | B43: =SUM(B39:B42) -> 0 | C43: =SUM(C39:C42) -> 0 | D43: =SUM(D39:D42) -> 0 | E43: =SUM(B43:D43) -> 0
A44: Flujo neto del mes | B44: =B38-B43 -> 0 | C44: =C38-C43 -> 0 | D44: =D38-D43 -> 0 | E44: =SUM(B44:D44) -> 0
A45: Saldo final del mes | B45: =B33+B44 -> 0 | C45: =C33+C44 -> 0 | D45: =D33+D44 -> 0 | E45: =D45 -> 0
A47: C. CONCILIACIÓN CON LOS REGISTROS DIARIOS (en USD)
A48: Concepto | B48: =Listas!$K$5 -> Octubre 2026 | C48: =Listas!$K$6 -> Noviembre 2026 | D48: =Listas!$K$7 -> Diciembre 2026 | E48: Total periodo
A49: Gastos pagados en efectivo (Gastos Diarios, método Efectivo) | B49: =SUMIFS('Gastos Diarios'!$F$35:$F$1049,'Gastos Diarios'!$E$35:$E$1049,"Efectivo",'Gastos Diarios'!$A$35:$A$1049,">="&Listas!$L$5,'Gastos Diarios'!$A$35:$A$1049,"<="&Listas!$M$5) -> 835.58499 | C49: =SUMIFS('Gastos Diarios'!$F$35:$F$1049,'Gastos Diarios'!$E$35:$E$1049,"Efectivo",'Gastos Diarios'!$A$35:$A$1049,">="&Listas!$L$6,'Gastos Diarios'!$A$35:$A$1049,"<="&Listas!$M$6) -> 0 | D49: =SUMIFS('Gastos Diarios'!$F$35:$F$1049,'Gastos Diarios'!$E$35:$E$1049,"Efectivo",'Gastos Diarios'!$A$35:$A$1049,">="&Listas!$L$7,'Gastos Diarios'!$A$35:$A$1049,"<="&Listas!$M$7) -> 0 | E49: =SUM(B49:D49) -> 835.58499
A50: Compras / pagos en efectivo (Caja, en USD) | B50: =SUMIFS('Caja Efectivo'!$L$6:$L$1005,'Caja Efectivo'!$B$6:$B$1005,"Compra / pago en efectivo",'Caja Efectivo'!$A$6:$A$1005,">="&Listas!$L$5,'Caja Efectivo'!$A$6:$A$1005,"<="&Listas!$M$5) -> 0 | C50: =SUMIFS('Caja Efectivo'!$L$6:$L$1005,'Caja Efectivo'!$B$6:$B$1005,"Compra / pago en efectivo",'Caja Efectivo'!$A$6:$A$1005,">="&Listas!$L$6,'Caja Efectivo'!$A$6:$A$1005,"<="&Listas!$M$6) -> 0 | D50: =SUMIFS('Caja Efectivo'!$L$6:$L$1005,'Caja Efectivo'!$B$6:$B$1005,"Compra / pago en efectivo",'Caja Efectivo'!$A$6:$A$1005,">="&Listas!$L$7,'Caja Efectivo'!$A$6:$A$1005,"<="&Listas!$M$7) -> 0 | E50: =SUM(B50:D50) -> 0
A51: Diferencia en gastos | B51: =B49-B50 -> 835.58499 | C51: =C49-C50 -> 0 | D51: =D49-D50 -> 0 | E51: =SUM(B51:D51) -> 835.58499
A52: Ingresos cobrados en efectivo (Ingresos Diarios, método Efectivo) | B52: =SUMIFS('Ingresos Diarios'!$H$27:$H$1026,'Ingresos Diarios'!$I$27:$I$1026,"Efectivo",'Ingresos Diarios'!$A$27:$A$1026,">="&Listas!$L$5,'Ingresos Diarios'!$A$27:$A$1026,"<="&Listas!$M$5) -> 823.89325 | C52: =SUMIFS('Ingresos Diarios'!$H$27:$H$1026,'Ingresos Diarios'!$I$27:$I$1026,"Efectivo",'Ingresos Diarios'!$A$27:$A$1026,">="&Listas!$L$6,'Ingresos Diarios'!$A$27:$A$1026,"<="&Listas!$M$6) -> 0 | D52: =SUMIFS('Ingresos Diarios'!$H$27:$H$1026,'Ingresos Diarios'!$I$27:$I$1026,"Efectivo",'Ingresos Diarios'!$A$27:$A$1026,">="&Listas!$L$7,'Ingresos Diarios'!$A$27:$A$1026,"<="&Listas!$M$7) -> 0 | E52: =SUM(B52:D52) -> 823.89325
A53: Ventas / cobros en efectivo (Caja, en USD) | B53: =SUMIFS('Caja Efectivo'!$L$6:$L$1005,'Caja Efectivo'!$B$6:$B$1005,"Venta / cobro en efectivo",'Caja Efectivo'!$A$6:$A$1005,">="&Listas!$L$5,'Caja Efectivo'!$A$6:$A$1005,"<="&Listas!$M$5) -> 654.78649 | C53: =SUMIFS('Caja Efectivo'!$L$6:$L$1005,'Caja Efectivo'!$B$6:$B$1005,"Venta / cobro en efectivo",'Caja Efectivo'!$A$6:$A$1005,">="&Listas!$L$6,'Caja Efectivo'!$A$6:$A$1005,"<="&Listas!$M$6) -> 0 | D53: =SUMIFS('Caja Efectivo'!$L$6:$L$1005,'Caja Efectivo'!$B$6:$B$1005,"Venta / cobro en efectivo",'Caja Efectivo'!$A$6:$A$1005,">="&Listas!$L$7,'Caja Efectivo'!$A$6:$A$1005,"<="&Listas!$M$7) -> 0 | E53: =SUM(B53:D53) -> 654.78649
A54: Diferencia en ingresos | B54: =B52-B53 -> 169.10675 | C54: =C52-C53 -> 0 | D54: =D52-D53 -> 0 | E54: =SUM(B54:D54) -> 169.10675
A55: Movimientos de caja marcados como NO registrados | B55: =COUNTIFS(#REF!,"No",'Caja Efectivo'!$A$6:$A$1005,">="&Listas!$L$5,'Caja Efectivo'!$A$6:$A$1005,"<="&Listas!$M$5) -> #VALUE! | C55: =COUNTIFS(#REF!,"No",'Caja Efectivo'!$A$6:$A$1005,">="&Listas!$L$6,'Caja Efectivo'!$A$6:$A$1005,"<="&Listas!$M$6) -> #VALUE! | D55: =COUNTIFS(#REF!,"No",'Caja Efectivo'!$A$6:$A$1005,">="&Listas!$L$7,'Caja Efectivo'!$A$6:$A$1005,"<="&Listas!$M$7) -> #VALUE! | E55: =SUM(B55:D55) -> #VALUE!
A56: Movimientos en colones sin tipo de cambio | B56: =COUNTIFS('Caja Efectivo'!$I$6:$I$1005,"CRC",'Caja Efectivo'!$K$6:$K$1005,"",'Caja Efectivo'!$J$6:$J$1005,">0",'Caja Efectivo'!$A$6:$A$1005,">="&Listas!$L$5,'Caja Efectivo'!$A$6:$A$1005,"<="&Listas!$M$5) -> 0 | C56: =COUNTIFS('Caja Efectivo'!$I$6:$I$1005,"CRC",'Caja Efectivo'!$K$6:$K$1005,"",'Caja Efectivo'!$J$6:$J$1005,">0",'Caja Efectivo'!$A$6:$A$1005,">="&Listas!$L$6,'Caja Efectivo'!$A$6:$A$1005,"<="&Listas!$M$6) -> 0 | D56: =COUNTIFS('Caja Efectivo'!$I$6:$I$1005,"CRC",'Caja Efectivo'!$K$6:$K$1005,"",'Caja Efectivo'!$J$6:$J$1005,">0",'Caja Efectivo'!$A$6:$A$1005,">="&Listas!$L$7,'Caja Efectivo'!$A$6:$A$1005,"<="&Listas!$M$7) -> 0 | E56: =SUM(B56:D56) -> 0
A57: Las diferencias deben ser cero: todo gasto o ingreso en efectivo va en su registro diario Y en la caja. En rojo = revisar qué falta en cuál de las dos hojas.
A60: D. CONTADOR PARA EL ARQUEO (escriba cuántos billetes y monedas hay)
A61: Dólares (USD) | B61: Cantidad | C61: Subtotal | E61: Colones (₡) | F61: Cantidad | G61: Subtotal
A62: 100 | C62: =A62*N(B62) -> 0 | E62: 20000 | G62: =E62*N(F62) -> 0
A63: 50 | C63: =A63*N(B63) -> 0 | E63: 10000 | G63: =E63*N(F63) -> 0
A64: 20 | C64: =A64*N(B64) -> 0 | E64: 5000 | G64: =E64*N(F64) -> 0
A65: 10 | C65: =A65*N(B65) -> 0 | E65: 2000 | G65: =E65*N(F65) -> 0
A66: 5 | C66: =A66*N(B66) -> 0 | E66: 1000 | G66: =E66*N(F66) -> 0
A67: 2 | C67: =A67*N(B67) -> 0 | E67: 500 | G67: =E67*N(F67) -> 0
A68: 1 | C68: =A68*N(B68) -> 0 | E68: 100 | G68: =E68*N(F68) -> 0
A69: 0.25 | C69: =A69*N(B69) -> 0 | E69: 50 | G69: =E69*N(F69) -> 0
A70: 0.1 | C70: =A70*N(B70) -> 0 | E70: 25 | G70: =E70*N(F70) -> 0
A71: 0.05 | C71: =A71*N(B71) -> 0 | E71: 10 | G71: =E71*N(F71) -> 0
A72: 0.01 | C72: =A72*N(B72) -> 0 | E72: 5 | G72: =E72*N(F72) -> 0
A73: Total contado USD | C73: =SUM(C62:C72) -> 0 | E73: Total contado ₡ | G73: =SUM(G62:G72) -> 0
A74: Diferencia vs. saldo actual | C74: =C73-$D$12 -> -654.78649 | E74: Diferencia vs. saldo actual | G74: =G73-$E$12 -> 0
A75: Después de contar, copie los totales en el registro de arqueos (sección E) y borre las cantidades para el próximo conteo. La diferencia compara contra el saldo de HOY según los registros.
A78: E. REGISTRO DE ARQUEOS (conteo físico del efectivo)
A79: Fecha del arqueo | B79: Moneda | C79: Saldo según registros | D79: Conteo físico | E79: Diferencia | F79: Contado por | G79: Revisado por | H79: ¿Se registró ajuste? | I79: Explicación de la diferencia
A80: 46326 | B80: USD | F80: Concierge | G80: Gerente general | H80: No aplica | I80: ← Ejemplo: fila de formato, puede borrarla
C81: =IF(OR(A81="",B81=""),"",IF(B81="USD",$C$6,$C$7)+SUMIFS('Caja Efectivo'!$J$6:$J$1005,'Caja Efectivo'!$I$6:$I$1005,B81,'Caja Efectivo'!$C$6:$C$1005,"Entrada",'Caja Efectivo'!$A$6:$A$1005,"<="&A81)-SUMIFS('Caja Efectivo'!$J$6:$J$1005,'Caja Efectivo'!$I$6:$I$1005,B81,'Caja Efectivo'!$C$6:$C$1005,"Salida",'Caja Efectivo'!$A$6:$A$1005,"<="&A81)) | E81: =IF(OR(C81="",D81=""),"",D81-C81)
C82: =IF(OR(A82="",B82=""),"",IF(B82="USD",$C$6,$C$7)+SUMIFS('Caja Efectivo'!$J$6:$J$1005,'Caja Efectivo'!$I$6:$I$1005,B82,'Caja Efectivo'!$C$6:$C$1005,"Entrada",'Caja Efectivo'!$A$6:$A$1005,"<="&A82)-SUMIFS('Caja Efectivo'!$J$6:$J$1005,'Caja Efectivo'!$I$6:$I$1005,B82,'Caja Efectivo'!$C$6:$C$1005,"Salida",'Caja Efectivo'!$A$6:$A$1005,"<="&A82)) | E82: =IF(OR(C82="",D82=""),"",D82-C82)
C83: =IF(OR(A83="",B83=""),"",IF(B83="USD",$C$6,$C$7)+SUMIFS('Caja Efectivo'!$J$6:$J$1005,'Caja Efectivo'!$I$6:$I$1005,B83,'Caja Efectivo'!$C$6:$C$1005,"Entrada",'Caja Efectivo'!$A$6:$A$1005,"<="&A83)-SUMIFS('Caja Efectivo'!$J$6:$J$1005,'Caja Efectivo'!$I$6:$I$1005,B83,'Caja Efectivo'!$C$6:$C$1005,"Salida",'Caja Efectivo'!$A$6:$A$1005,"<="&A83)) | E83: =IF(OR(C83="",D83=""),"",D83-C83)
C84: =IF(OR(A84="",B84=""),"",IF(B84="USD",$C$6,$C$7)+SUMIFS('Caja Efectivo'!$J$6:$J$1005,'Caja Efectivo'!$I$6:$I$1005,B84,'Caja Efectivo'!$C$6:$C$1005,"Entrada",'Caja Efectivo'!$A$6:$A$1005,"<="&A84)-SUMIFS('Caja Efectivo'!$J$6:$J$1005,'Caja Efectivo'!$I$6:$I$1005,B84,'Caja Efectivo'!$C$6:$C$1005,"Salida",'Caja Efectivo'!$A$6:$A$1005,"<="&A84)) | E84: =IF(OR(C84="",D84=""),"",D84-C84)
C85: =IF(OR(A85="",B85=""),"",IF(B85="USD",$C$6,$C$7)+SUMIFS('Caja Efectivo'!$J$6:$J$1005,'Caja Efectivo'!$I$6:$I$1005,B85,'Caja Efectivo'!$C$6:$C$1005,"Entrada",'Caja Efectivo'!$A$6:$A$1005,"<="&A85)-SUMIFS('Caja Efectivo'!$J$6:$J$1005,'Caja Efectivo'!$I$6:$I$1005,B85,'Caja Efectivo'!$C$6:$C$1005,"Salida",'Caja Efectivo'!$A$6:$A$1005,"<="&A85)) | E85: =IF(OR(C85="",D85=""),"",D85-C85)
C86: =IF(OR(A86="",B86=""),"",IF(B86="USD",$C$6,$C$7)+SUMIFS('Caja Efectivo'!$J$6:$J$1005,'Caja Efectivo'!$I$6:$I$1005,B86,'Caja Efectivo'!$C$6:$C$1005,"Entrada",'Caja Efectivo'!$A$6:$A$1005,"<="&A86)-SUMIFS('Caja Efectivo'!$J$6:$J$1005,'Caja Efectivo'!$I$6:$I$1005,B86,'Caja Efectivo'!$C$6:$C$1005,"Salida",'Caja Efectivo'!$A$6:$A$1005,"<="&A86)) | E86: =IF(OR(C86="",D86=""),"",D86-C86)
C87: =IF(OR(A87="",B87=""),"",IF(B87="USD",$C$6,$C$7)+SUMIFS('Caja Efectivo'!$J$6:$J$1005,'Caja Efectivo'!$I$6:$I$1005,B87,'Caja Efectivo'!$C$6:$C$1005,"Entrada",'Caja Efectivo'!$A$6:$A$1005,"<="&A87)-SUMIFS('Caja Efectivo'!$J$6:$J$1005,'Caja Efectivo'!$I$6:$I$1005,B87,'Caja Efectivo'!$C$6:$C$1005,"Salida",'Caja Efectivo'!$A$6:$A$1005,"<="&A87)) | E87: =IF(OR(C87="",D87=""),"",D87-C87)
C88: =IF(OR(A88="",B88=""),"",IF(B88="USD",$C$6,$C$7)+SUMIFS('Caja Efectivo'!$J$6:$J$1005,'Caja Efectivo'!$I$6:$I$1005,B88,'Caja Efectivo'!$C$6:$C$1005,"Entrada",'Caja Efectivo'!$A$6:$A$1005,"<="&A88)-SUMIFS('Caja Efectivo'!$J$6:$J$1005,'Caja Efectivo'!$I$6:$I$1005,B88,'Caja Efectivo'!$C$6:$C$1005,"Salida",'Caja Efectivo'!$A$6:$A$1005,"<="&A88)) | E88: =IF(OR(C88="",D88=""),"",D88-C88)
C89: =IF(OR(A89="",B89=""),"",IF(B89="USD",$C$6,$C$7)+SUMIFS('Caja Efectivo'!$J$6:$J$1005,'Caja Efectivo'!$I$6:$I$1005,B89,'Caja Efectivo'!$C$6:$C$1005,"Entrada",'Caja Efectivo'!$A$6:$A$1005,"<="&A89)-SUMIFS('Caja Efectivo'!$J$6:$J$1005,'Caja Efectivo'!$I$6:$I$1005,B89,'Caja Efectivo'!$C$6:$C$1005,"Salida",'Caja Efectivo'!$A$6:$A$1005,"<="&A89)) | E89: =IF(OR(C89="",D89=""),"",D89-C89)
C90: =IF(OR(A90="",B90=""),"",IF(B90="USD",$C$6,$C$7)+SUMIFS('Caja Efectivo'!$J$6:$J$1005,'Caja Efectivo'!$I$6:$I$1005,B90,'Caja Efectivo'!$C$6:$C$1005,"Entrada",'Caja Efectivo'!$A$6:$A$1005,"<="&A90)-SUMIFS('Caja Efectivo'!$J$6:$J$1005,'Caja Efectivo'!$I$6:$I$1005,B90,'Caja Efectivo'!$C$6:$C$1005,"Salida",'Caja Efectivo'!$A$6:$A$1005,"<="&A90)) | E90: =IF(OR(C90="",D90=""),"",D90-C90)
C91: =IF(OR(A91="",B91=""),"",IF(B91="USD",$C$6,$C$7)+SUMIFS('Caja Efectivo'!$J$6:$J$1005,'Caja Efectivo'!$I$6:$I$1005,B91,'Caja Efectivo'!$C$6:$C$1005,"Entrada",'Caja Efectivo'!$A$6:$A$1005,"<="&A91)-SUMIFS('Caja Efectivo'!$J$6:$J$1005,'Caja Efectivo'!$I$6:$I$1005,B91,'Caja Efectivo'!$C$6:$C$1005,"Salida",'Caja Efectivo'!$A$6:$A$1005,"<="&A91)) | E91: =IF(OR(C91="",D91=""),"",D91-C91)
C92: =IF(OR(A92="",B92=""),"",IF(B92="USD",$C$6,$C$7)+SUMIFS('Caja Efectivo'!$J$6:$J$1005,'Caja Efectivo'!$I$6:$I$1005,B92,'Caja Efectivo'!$C$6:$C$1005,"Entrada",'Caja Efectivo'!$A$6:$A$1005,"<="&A92)-SUMIFS('Caja Efectivo'!$J$6:$J$1005,'Caja Efectivo'!$I$6:$I$1005,B92,'Caja Efectivo'!$C$6:$C$1005,"Salida",'Caja Efectivo'!$A$6:$A$1005,"<="&A92)) | E92: =IF(OR(C92="",D92=""),"",D92-C92)
... C120: =IF(OR(A120="",B120=""),"",IF(B120="USD",$C$6,$C$7)+SUMIFS('Caja Efectivo'!$J$6:$J$1005,'Caja Efectivo'!$I$6:$I$1005,B120,'Caja Efectivo'!$C$6:$C$1005,"Entrada",'Caja Efectivo'!$A$6:$A$1005,"<="&A120)-SUMIFS('Caja Efectivo'!$J$6:$J$1005,'Caja Efectivo'!$I$6:$I$1005,B120,'Caja Efectivo'!$C$6:$C$1005,"Salida",'Caja Efectivo'!$A$6:$A$1005,"<="&A120)) | E120: =IF(OR(C120="",D120=""),"",D120-C120)
A122: Regla: se hace arqueo al menos una vez por semana y siempre al cierre de mes, con dos personas. Si hay diferencia, se explica aquí y se registra un 'Ajuste de arqueo (+)' o '(−)' en la hoja Caja Efectivo para que el saldo coincida con el dinero real.

Sheet Utilidad y Posibles Gastos
A1: Utilidad y Posibles Gastos · 05/10/2026 – 31/12/2026
A2: Utilidad real (desde los registros diarios), presupuesto de posibles gastos por categoría y proyección de utilidad.
A4: A. UTILIDAD REAL POR MES
A5: Concepto | B5: =Listas!$K$5 -> Octubre 2026 | C5: =Listas!$K$6 -> Noviembre 2026 | D5: =Listas!$K$7 -> Diciembre 2026 | E5: Total
A6: Ingresos reales | B6: ='Gastos e Ingresos'!B10 -> 27531.466 | C6: ='Gastos e Ingresos'!C10 -> 0 | D6: ='Gastos e Ingresos'!D10 -> 0 | E6: ='Gastos e Ingresos'!E10 -> 27531.466
A7: Gastos reales | B7: ='Gastos e Ingresos'!B25 -> 38170 | C7: ='Gastos e Ingresos'!C25 -> 0 | D7: ='Gastos e Ingresos'!D25 -> 0 | E7: ='Gastos e Ingresos'!E25 -> 38170
A8: UTILIDAD REAL | B8: =B6-B7 -> -10638.534 | C8: =C6-C7 -> 0 | D8: =D6-D7 -> 0 | E8: =E6-E7 -> -10638.534
A9: Margen real (%) | B9: =IF(B6=0,0,B8/B6) -> -0.38641363 | C9: =IF(C6=0,0,C8/C6) -> 0 | D9: =IF(D6=0,0,D8/D6) -> 0 | E9: =IF(E6=0,0,E8/E6) -> -0.38641363
A11: B. POSIBLES GASTOS (PRESUPUESTO) VS GASTO REAL
A12: Categoría | B12: ="Ppto "&Listas!$K$5 -> Ppto Octubre 2026 | C12: ="Ppto "&Listas!$K$6 -> Ppto Noviembre 2026 | D12: ="Ppto "&Listas!$K$7 -> Ppto Diciembre 2026 | E12: Total presupuestado | F12: Gasto real (acumulado) | G12: Diferencia (Ppto − Real) | H12: % ejecutado
A13: =Listas!$A$5 -> Nómina y salarios | E13: =SUM(B13:D13) -> 0 | F13: ='Gastos e Ingresos'!E13 -> 2167 | G13: =E13-F13 -> -2167 | H13: =IF(E13=0,0,F13/E13) -> 0
A14: =Listas!$A$6 -> Cargas sociales (CCSS/INS) | E14: =SUM(B14:D14) -> 0 | F14: ='Gastos e Ingresos'!E14 -> 564 | G14: =E14-F14 -> -564 | H14: =IF(E14=0,0,F14/E14) -> 0
A15: =Listas!$A$7 -> Servicios públicos e internet | E15: =SUM(B15:D15) -> 0 | F15: ='Gastos e Ingresos'!E15 -> 2825 | G15: =E15-F15 -> -2825 | H15: =IF(E15=0,0,F15/E15) -> 0
A16: =Listas!$A$8 -> Mantenimiento y reparaciones | E16: =SUM(B16:D16) -> 0 | F16: ='Gastos e Ingresos'!E16 -> 3548 | G16: =E16-F16 -> -3548 | H16: =IF(E16=0,0,F16/E16) -> 0
A17: =Listas!$A$9 -> Limpieza y lavandería | E17: =SUM(B17:D17) -> 0 | F17: ='Gastos e Ingresos'!E17 -> 469 | G17: =E17-F17 -> -469 | H17: =IF(E17=0,0,F17/E17) -> 0
A18: =Listas!$A$10 -> Suministros y amenities | E18: =SUM(B18:D18) -> 0 | F18: ='Gastos e Ingresos'!E18 -> 542 | G18: =E18-F18 -> -542 | H18: =IF(E18=0,0,F18/E18) -> 0
A19: =Listas!$A$11 -> Alimentos y bebidas | E19: =SUM(B19:D19) -> 0 | F19: ='Gastos e Ingresos'!E19 -> 8662 | G19: =E19-F19 -> -8662 | H19: =IF(E19=0,0,F19/E19) -> 0
A20: =Listas!$A$12 -> Comisiones de plataformas | E20: =SUM(B20:D20) -> 0 | F20: ='Gastos e Ingresos'!E20 -> 321 | G20: =E20-F20 -> -321 | H20: =IF(E20=0,0,F20/E20) -> 0
A21: =Listas!$A$13 -> Marketing y publicidad | E21: =SUM(B21:D21) -> 0 | F21: ='Gastos e Ingresos'!E21 -> 8000 | G21: =E21-F21 -> -8000 | H21: =IF(E21=0,0,F21/E21) -> 0
A22: =Listas!$A$14 -> Costo de tours y actividades | E22: =SUM(B22:D22) -> 0 | F22: ='Gastos e Ingresos'!E22 -> 2588 | G22: =E22-F22 -> -2588 | H22: =IF(E22=0,0,F22/E22) -> 0
A23: =Listas!$A$15 -> Seguros | E23: =SUM(B23:D23) -> 0 | F23: ='Gastos e Ingresos'!E23 -> 2194 | G23: =E23-F23 -> -2194 | H23: =IF(E23=0,0,F23/E23) -> 0
A24: =Listas!$A$16 -> Impuestos y patentes | E24: =SUM(B24:D24) -> 0 | F24: ='Gastos e Ingresos'!E24 -> 6290 | G24: =E24-F24 -> -6290 | H24: =IF(E24=0,0,F24/E24) -> 0
A25: =Listas!$A$17 -> Combustible y transporte | E25: =SUM(B25:D25) -> 0 | F25: =#REF! -> #REF! | G25: =E25-F25 -> #REF! | H25: =IF(E25=0,0,F25/E25) -> 0
A26: =Listas!$A$18 -> Jardinería y piscinas | E26: =SUM(B26:D26) -> 0 | F26: =#REF! -> #REF! | G26: =E26-F26 -> #REF! | H26: =IF(E26=0,0,F26/E26) -> 0
A27: =Listas!$A$19 -> Software y tecnología | E27: =SUM(B27:D27) -> 0 | F27: =#REF! -> #REF! | G27: =E27-F27 -> #REF! | H27: =IF(E27=0,0,F27/E27) -> 0
A28: =Listas!$A$20 -> Imprevistos y otros | E28: =SUM(B28:D28) -> 0 | F28: =#REF! -> #REF! | G28: =E28-F28 -> #REF! | H28: =IF(E28=0,0,F28/E28) -> 0
A29: TOTAL POSIBLES GASTOS | B29: =SUM(B13:B28) -> 0 | C29: =SUM(C13:C28) -> 0 | D29: =SUM(D13:D28) -> 0 | E29: =SUM(E13:E28) -> 0 | F29: =SUM(F13:F28) -> #REF! | G29: =SUM(G13:G28) -> #REF! | H29: =IF(E29=0,0,F29/E29) -> 0
A30: Celdas amarillas/azules = supuestos editables. Los montos son ESTIMACIONES DE EJEMPLO (no provienen del sitio web): reemplácelos con su presupuesto real. Octubre solo cuenta desde el día 5.
A32: C. UTILIDAD PROYECTADA VS REAL
A33: Concepto | B33: =Listas!$K$5 -> Octubre 2026 | C33: =Listas!$K$6 -> Noviembre 2026 | D33: =Listas!$K$7 -> Diciembre 2026 | E33: Total
A34: Ingresos proyectados (supuesto) | B34: 30000 | C34: 34000 | D34: 65000 | E34: =SUM(B34:D34) -> 129000
A35: Gastos proyectados (posibles gastos) | B35: =B29 -> 0 | C35: =C29 -> 0 | D35: =D29 -> 0 | E35: =SUM(B35:D35) -> 0
A36: UTILIDAD PROYECTADA | B36: =B34-B35 -> 30000 | C36: =C34-C35 -> 34000 | D36: =D34-D35 -> 65000 | E36: =E34-E35 -> 129000
A37: Margen proyectado (%) | B37: =IF(B34=0,0,B36/B34) -> 1 | C37: =IF(C34=0,0,C36/C34) -> 1 | D37: =IF(D34=0,0,D36/D34) -> 1 | E37: =IF(E34=0,0,E36/E34) -> 1
A38: Utilidad real | B38: =B8 -> -10638.534 | C38: =C8 -> 0 | D38: =D8 -> 0 | E38: =E8 -> -10638.534
A39: Diferencia: Real − Proyectada | B39: =B38-B36 -> -40638.534 | C39: =C38-C36 -> -34000 | D39: =D38-D36 -> -65000 | E39: =E38-E36 -> -139638.53
A40: Ingresos proyectados: estimación de ejemplo (temporada baja oct–nov, alta en diciembre). Reemplácela con su meta real.

Sheet Listas
A1: Listas y parámetros
A2: Edite estas listas (azul) para cambiar los desplegables. Las villas se tomaron de canavidaresort.com. Moneda de trabajo: USD (supuesto; el sitio muestra EUR, cámbiela si lo prefiere).
A4: Categorías de gasto | C4: Categorías de ingreso | E4: Villas / unidades | G4: Canal de reserva | I4: Método de pago | K4: Mes | L4: Inicio | M4: Fin | N4: Días | P4: Tipo de movimiento de caja | Q4: Dirección | S4: Moneda de caja | U4: Categoría (caja)
A5: Nómina y salarios | C5: Hospedaje | E5: Loro (4 hab) | G5: Directo / WhatsApp | I5: Efectivo | K5: Octubre 2026 | L5: 46300 | M5: 46326 | N5: =M5-L5+1 -> 27 | P5: Venta / cobro en efectivo | Q5: Entrada | S5: USD | U5: =IF(Listas!$C$5="","",Listas!$C$5) -> Hospedaje
A6: Cargas sociales (CCSS/INS) | C6: Tours y actividades | E6: Love Nest | G6: Web (Lodgify) | I6: Tarjeta | K6: Noviembre 2026 | L6: 46327 | M6: 46356 | N6: =M6-L6+1 -> 30 | P6: Retiro de banco a caja | Q6: Entrada | S6: CRC | U6: =IF(Listas!$C$6="","",Listas!$C$6) -> Tours y actividades
A7: Servicios públicos e internet | C7: Alimentos y bebidas | E7: Caracara (2 hab) | G7: Airbnb | I7: Transferencia / SINPE | K7: Diciembre 2026 | L7: 46357 | M7: 46387 | N7: =M7-L7+1 -> 31 | P7: Otra entrada de efectivo | Q7: Entrada | U7: =IF(Listas!$C$7="","",Listas!$C$7) -> Alimentos y bebidas
A8: Mantenimiento y reparaciones | C8: Extra Guest Fee | E8: Oropendola (2 hab) | G8: Booking.com | I8: Paypal | K8: Total periodo | N8: =SUM(N5:N7) -> 88 | P8: Ajuste de arqueo (+) | Q8: Entrada | U8: =IF(Listas!$C$8="","",Listas!$C$8) -> Extra Guest Fee
A9: Limpieza y lavandería | C9: Mascota | E9: Toucan (3 hab) | G9: Expedia | I9: Email Transfer | P9: Compra / pago en efectivo | Q9: Salida | U9: =IF(Listas!$C$9="","",Listas!$C$9) -> Mascota
A10: Suministros y amenities | C10: Early/Late Check Out | E10: Torogoz (4 hab) | K10: Periodo analizado: 05/10/2026 a 31/12/2026 (octubre inicia el día 5). | P10: Depósito de caja al banco | Q10: Salida | U10: =IF(Listas!$A$5="","",Listas!$A$5) -> Nómina y salarios
A11: Alimentos y bebidas | C11: Cleaning Fee | E11: Quetzal (4 hab) | P11: Vale / adelanto | Q11: Salida | U11: =IF(Listas!$A$6="","",Listas!$A$6) -> Cargas sociales (CCSS/INS)
A12: Comisiones de plataformas | E12: Lapa (3 hab) | P12: Ajuste de arqueo (−) | Q12: Salida | U12: =IF(Listas!$A$7="","",Listas!$A$7) -> Servicios públicos e internet
A13: Marketing y publicidad | E13: Cusinga (1 hab) | U13: =IF(Listas!$A$8="","",Listas!$A$8) -> Mantenimiento y reparaciones
A14: Costo de tours y actividades | E14: Gecko (Condo 3) | U14: =IF(Listas!$A$9="","",Listas!$A$9) -> Limpieza y lavandería
A15: Seguros | E15: Salamandra (Condo 4) | U15: =IF(Listas!$A$10="","",Listas!$A$10) -> Suministros y amenities
A16: Impuestos y patentes | E16: Rana (Condo 6) | U16: =IF(Listas!$A$11="","",Listas!$A$11) -> Alimentos y bebidas
A17: Combustible y transporte | E17: Iguana (Condo 2) | U17: =IF(Listas!$A$12="","",Listas!$A$12) -> Comisiones de plataformas
A18: Jardinería y piscinas | E18: Lizardo (Condo 5) | U18: =IF(Listas!$A$13="","",Listas!$A$13) -> Marketing y publicidad
A19: Software y tecnología | E19: Colibri | U19: =IF(Listas!$A$14="","",Listas!$A$14) -> Costo de tours y actividades
A20: Imprevistos y otros | E20: Tortuga | U20: =IF(Listas!$A$15="","",Listas!$A$15) -> Seguros
A21: Muebleria | E21: Recepcion | U21: =IF(Listas!$A$16="","",Listas!$A$16) -> Impuestos y patentes
E22: Pavon | U22: =IF(Listas!$A$17="","",Listas!$A$17) -> Combustible y transporte
U23: =IF(Listas!$A$18="","",Listas!$A$18) -> Jardinería y piscinas
U24: =IF(Listas!$A$19="","",Listas!$A$19) -> Software y tecnología
U25: =IF(Listas!$A$20="","",Listas!$A$20) -> Imprevistos y otros
U26: Movimiento interno (banco ↔ caja)
P28: Listas de la hoja Caja Efectivo. La categoría (caja) toma sola las categorías de ingreso y de gasto de este libro.
